{
 "ha": {
  "mai": "may",
  "farin": "white",
  "ciki": "abdomen",
  "mutumin": "the man",
  "ya": "daughter",
  "aiki": "job",
  "shawarar": "the decision",
  "mugaye": "evil",
  "ko": "or",
  "yă": "daughter",
  "yi": "do",
  "abin": "the thing",
  "zunubi": "sin",
  "suke": "they are",
  "zauna": "inhabit",
  "tare": "repel",
  "yin": "do",
  "ba'a": "mocking",
  "amma": "but",
  "jin": "feeling",
  "daɗin": "enjoy",
  "bin": "follow",
  "dokar": "the law",
  "yeahoh": "yeahoh",
  "ta": "facing",
  "nazarinta": "her analysis",
  "dare": "night",
  "rana": "day",
  "kama": "arrest",
  "itacen": "the tree",
  "aka": "aka",
  "shuka": "sow",
  "kusa": "almost",
  "maɓulɓulan": "the sources",
  "wanda": "that",
  "yake": "it is",
  "amfani": "benefit",
  "a": "in",
  "daidai": "equal",
  "ganyensa": "its leaves",
  "sa": "ox",
  "bushewa": "dryness",
  "yakan": "he used to",
  "nasara": "victory",
  "haka": "so",
  "su": "they",
  "yayi": "he did",
  "iska": "air",
  "take": "title",
  "kwashewa": "take away",
  "za": "will",
  "iya": "can",
  "tsayawa": "stay",
  "shari'a": "sharia",
  "balle": "let alone",
  "sami": "find",
  "taron": "the event",
  "adalai": "righteous",
  "gama": "complete",
  "lura": "treatment",
  "yadda": "how",
  "abubuwa": "things",
  "ayyukan": "the works",
  "ga": "ga",
  "hallaka": "destroy",
  "me": "what",
  "haɗa": "connect",
  "baki": "mouth",
  "ƙulla": "tie",
  "shawarwarin": "the recommendations",
  "banza": "nonsense",
  "sarakunan": "the kings",
  "sun": "sun",
  "ɗauki": "take",
  "matsayi": "status",
  "taru": "come together",
  "gaba": "front",
  "gāba": "front",
  "shafaffensa": "his anointed",
  "cewa": "saying",
  "bari": "let",
  "mu": "we",
  "tsittsinke": "quiet",
  "sarƙoƙinsu": "their chains",
  "yantar": "free",
  "kamammu": "caught us",
  "kangin": "kangin",
  "bautar": "slavery",
  "allah": "god",
  "kursiyi": "the throne",
  "sama": "sky",
  "dariya": "laugh",
  "musu": "them",
  "sa'an": "then",
  "tsawata": "rebuke",
  "fushinsa": "his anger",
  "razanar": "razaran",
  "hasalarsa": "his talent",
  "na": "na",
  "sarkina": "my king",
  "kan": "against",
  "sihiyona": "zion",
  "dutsena": "my mountain",
  "tsarki": "holiness",
  "sarki": "king",
  "shelar": "announce",
  "umarnin": "the instructions",
  "ce": "say",
  "mini": "mini",
  "ɗana": "my son",
  "mahaifinka": "your father",
  "ka": "you",
  "tambaye": "asked",
  "ni": "me",
  "zan": "i will",
  "kuwa": "too",
  "al'ummai": "nations",
  "gādonka": "your inheritance",
  "iyakokin": "the limits",
  "mallakarka": "your property",
  "mulkinsu": "their rule",
  "sandan": "the rod",
  "ƙarfe": "metal",
  "farfashe": "broken",
  "kucu": "come in",
  "tukunyar": "the pot",
  "laka": "mud",
  "ku": "you",
  "sarakuna": "kings",
  "wayo": "clever",
  "shiga": "enter",
  "hankalinku": "your mind",
  "bauta": "worship",
  "wa": "brother",
  "tsoro": "fear",
  "kuna": "you are",
  "rawar": "role",
  "jiki": "body",
  "sumbaci": "kiss",
  "don": "for",
  "kada": "alligator",
  "fushi": "rage",
  "abubuwan": "the things",
  "kuke": "you are",
  "zai": "will",
  "farat": "flat",
  "dukan": "all",
  "mafaka": "refuge",
  "gare": "for",
  "shi": "he",
  "zabura": "psalm",
  "dawuda": "david",
  "sa'ad": "when",
  "gudu": "flee",
  "ɗansa": "his son",
  "absalom": "absalom",
  "abokan": "friends",
  "gābana": "against me",
  "yawa": "lot",
  "kaina": "myself",
  "cece": "saved",
  "sela": "cell",
  "garkuwa": "shield",
  "kewaye": "around",
  "ɗaukaka": "glory",
  "ɗaga": "defer",
  "amsa": "answer",
  "tudunsa": "his hill",
  "kwanta": "lie",
  "barci": "sleep",
  "farka": "revive",
  "kiyaye": "keep",
  "ji": "hearing",
  "dubu": "thousand",
  "goma": "ten",
  "ja": "avert",
  "dāgā": "from",
  "kowane": "every",
  "gefe": "edge",
  "tashi": "departure",
  "allahna": "my god",
  "bugi": "beat",
  "muƙamuƙi": "jaw",
  "kakkarya": "kakkarya",
  "haƙoran": "the teeth",
  "wurin": "the place",
  "ceto": "salvation",
  "zo": "come",
  "albarkanka": "your blessing",
  "mutanenka": "your people",
  "bi": "follow",
  "kaɗe": "beat",
  "kayan": "the goods",
  "kiɗi": "money",
  "tsirkiya": "chord",
  "kira": "call",
  "adalci": "justice",
  "sauƙi": "relief",
  "wahalata": "my trouble",
  "tausayina": "my pity",
  "addu'ata": "my prayer",
  "har": "until",
  "yaushe": "when",
  "ɗaukakata": "my glory",
  "kunya": "shame",
  "ƙaunaci": "love",
  "ruɗu": "delusion",
  "nemi": "seek",
  "allolin": "the gods",
  "ƙarya": "lie",
  "san": "know",
  "keɓe": "reservation",
  "tsoron": "the fear",
  "kansa": "himself",
  "fushinku": "your anger",
  "gadajenku": "your beds",
  "bincike": "research",
  "zukatanku": "your hearts",
  "shiru": "silence",
  "miƙa": "extend",
  "hadayun": "the offerings",
  "dace": "appropriate",
  "dogara": "dependence",
  "yawanci": "majority",
  "mana": "us",
  "alheri": "grace",
  "hasken": "the light",
  "fuskarka": "your face",
  "haskaka": "illuminate",
  "kanmu": "ourselves",
  "cika": "fill",
  "zuciyata": "my heart",
  "hatsinsu": "their grain",
  "sabon": "new",
  "ruwan": "the water",
  "inabinsu": "their grapes",
  "in": "if",
  "lafiya": "health",
  "kaɗai": "alone",
  "kake": "you are",
  "mazaunina": "my residence",
  "lau": "lau",
  "busa": "swell",
  "saurare": "listen",
  "kalmomina": "my words",
  "ajiyar": "the deposit",
  "kukata": "refuse",
  "nake": "i am",
  "addu'a": "prayer",
  "safe": "morning",
  "muryata": "my voice",
  "gabatar": "present",
  "bukatuna": "my needs",
  "gabanka": "in front of you",
  "jira": "wait",
  "zuciya": "heart",
  "allahn": "the god",
  "mugu": "bad",
  "kana": "you are",
  "aikata": "do",
  "mugunta": "evil",
  "fariya": "pride",
  "tsaya": "stand",
  "ƙin": "refuse",
  "kakan": "grandfather",
  "kisankai": "murder",
  "ƙyama": "disgust",
  "jinƙanka": "your mercy",
  "gidanka": "your house",
  "bangirma": "bangirma",
  "durƙusa": "bow",
  "haikalinka": "your temple",
  "adalcinka": "your righteousness",
  "fayyace": "clarify",
  "hanyarka": "your way",
  "gabana": "in front of me",
  "babu": "without",
  "kalma": "word",
  "bakinsu": "their mouths",
  "ita": "she",
  "marmarinsu": "their desires",
  "hallakar": "destruction",
  "waɗansu": "some",
  "maƙogwaronsu": "their throats",
  "buɗaɗɗen": "open",
  "kabari": "grave",
  "harshensu": "their language",
  "faɗin": "the width",
  "furta": "state",
  "laifi": "fault",
  "makircinsu": "their plot",
  "fāɗuwarsu": "their fall",
  "kore": "banish",
  "zunubansu": "their sins",
  "tayar": "tire",
  "maka": "for you",
  "murna": "joy",
  "rerawa": "singing",
  "buɗe": "open",
  "kāriyarka": "your protection",
  "bisansu": "after them",
  "domin": "because",
  "ƙaunar": "love",
  "sunanka": "your name",
  "cikinka": "inside you",
  "tabbatacce": "convincing",
  "albarkaci": "influence",
  "tagomashinka": "your favor",
  "bisa": "above",
  "sheminit": "seminite",
  "fushinka": "your anger",
  "hore": "trained",
  "hasalarka": "your talent",
  "jinƙai": "mercy",
  "suma": "faint",
  "warkar": "heal",
  "ƙasusuwana": "my bones",
  "zafin": "the pain",
  "ciwo": "injury",
  "raina": "despise",
  "wahala": "bother",
  "juyo": "turn around",
  "madawwamiyar": "eternal",
  "ƙaunarka": "your love",
  "tuna": "remember",
  "mutu": "die",
  "ke": "you",
  "yabonka": "your praise",
  "gaji": "tired",
  "tiƙis": "tick",
  "nishi": "groan",
  "jiƙe": "get wet",
  "gadona": "my bed",
  "kujerata": "my chair",
  "hawaye": "tears",
  "idanuna": "my eyes",
  "rasa": "lose",
  "baƙin": "the guest",
  "tafi": "go",
  "dukanku": "all of you",
  "jinƙansa": "his mercy",
  "karɓi": "accept",
  "sha": "drink",
  "karaya": "fracture",
  "juya": "turn",
  "wani": "anybody",
  "shiggayiyon": "the participants",
  "rera": "sing",
  "game": "beard",
  "kush": "whoosh",
  "benyamin": "benjamin",
  "wurinka": "your place",
  "kuɓutar": "escape",
  "yayyage": "torn",
  "zaki": "lion",
  "ɓarke": "tear",
  "kuskure": "mistake",
  "hannuwana": "my hands",
  "zaman": "session",
  "dalilin": "the reason",
  "cuci": "hurt",
  "abokin": "friend",
  "to": "so",
  "cim": "accomplish",
  "tattake": "trampled",
  "kwana": "angle",
  "ƙura": "dust",
  "fushin": "the anger",
  "umarta": "her command",
  "shari'ar": "the case",
  "shari'anta": "her case",
  "adalcina": "my justice",
  "mutuncina": "my honor",
  "binciken": "the investigation",
  "tunani": "thought",
  "zukata": "hearts",
  "kawo": "bring",
  "ƙarshen": "the end",
  "rikicin": "the crisis",
  "garkuwata": "my shield",
  "ceton": "rescue",
  "tsabtar": "clean",
  "alƙali": "judge",
  "bayyana": "appear",
  "kowace": "each",
  "mutum": "man",
  "bai": "no",
  "tuba": "repentance",
  "wasa": "game",
  "takobinsa": "his sword",
  "tanƙware": "bent over",
  "ɗaura": "arrest",
  "bakansa": "his bow",
  "shirya": "prepare",
  "makamansa": "his weapons",
  "dafi": "poison",
  "kibiyoyinsa": "his arrows",
  "wuta": "fire",
  "damuwa": "worry",
  "haifi": "give birth",
  "haƙa": "dig",
  "rami": "hole",
  "fāɗa": "say",
  "ramin": "the hole",
  "damuwar": "the worry",
  "sāke": "again",
  "nannaɗe": "wrapped up",
  "fitinarsa": "his trial",
  "takan": "step",
  "sauka": "alight",
  "gode": "thank",
  "adalcinsa": "his justice",
  "yabo": "praise",
  "shugabanmu": "our leader",
  "ɗaukakarka": "your glory",
  "sammai": "the heavens",
  "leɓunan": "the lips",
  "jarirai": "babies",
  "gābanka": "against you",
  "ɗaukan": "take",
  "fansa": "ransom",
  "dubi": "look",
  "aikin": "the work",
  "yatsotsinka": "your fingers",
  "taurari": "stars",
  "ajiye": "keep",
  "wurarensu": "their places",
  "wane": "which",
  "tunawa": "remembering",
  "kaɗan": "slightly",
  "masa": "him",
  "rawani": "crown",
  "kome": "everything",
  "ƙarƙashin": "under",
  "ƙafafunsa": "his feet",
  "tumaki": "sheep",
  "namun": "however",
  "jeji": "desert",
  "tsuntsayen": "the birds",
  "kifin": "fish",
  "teku": "sea",
  "yawo": "promenade",
  "muryar": "the voice",
  "mutuwar": "death",
  "ɗa": "son",
  "yabe": "praise",
  "banmamakinka": "your amazing",
  "baya": "behind",
  "tuntuɓe": "stumbling",
  "tabbata": "affirm",
  "gaskiyata": "my truth",
  "kujerarka": "your seat",
  "shafe": "erase",
  "sunansu": "their name",
  "abada": "ever",
  "abadin": "eternity",
  "lalaci": "laziness",
  "marar": "no",
  "ƙarewa": "ending",
  "cimma": "overtake",
  "gābanmu": "in front of us",
  "tuttumɓuke": "stumps",
  "biranensu": "their cities",
  "ma": "too",
  "ƙara": "increase",
  "tunaninsu": "their thoughts",
  "kujerarsa": "his seat",
  "hukunta": "judge",
  "gaskiya": "truth",
  "mafakan": "the asylum",
  "danniya": "stress",
  "lokutan": "the times",
  "taɓa": "touch",
  "yashe": "abandoned",
  "nemanka": "looking for you",
  "yabai": "thank you",
  "kisa": "execution",
  "ƙyale": "neglect",
  "kukan": "cry",
  "tsananta": "aggravate",
  "ƙofofin": "the doors",
  "mutuwa": "death",
  "yabanka": "praise you",
  "yar": "participant",
  "can": "there",
  "cetonka": "your salvation",
  "al'umma": "nation",
  "ƙafafunsu": "their feet",
  "ragar": "net",
  "ɓoye": "conceal",
  "an": "an",
  "gaskiyarsa": "his truth",
  "hannuwansu": "their hands",
  "koma": "return",
  "al'umman": "the community",
  "manta": "forget",
  "bukata": "need",
  "zuciyar": "the heart",
  "bar": "bar",
  "buge": "hit",
  "kurum": "kurum",
  "nesa": "distance",
  "kanka": "yourself",
  "fariyarsa": "his pride",
  "mugun": "evil",
  "marasa": "the ones who don't",
  "makircin": "the scheme",
  "taƙama": "boast",
  "ƙulle": "bar",
  "ƙullen": "the lock",
  "zuciyarsa": "his heart",
  "haɗama": "greed",
  "tunaninsa": "his thoughts",
  "dama": "agitate",
  "hanyoyinsa": "his methods",
  "sukan": "sukan",
  "girman": "the size",
  "dokokinka": "your laws",
  "gābansa": "in front of him",
  "duban": "the look",
  "reni": "nurse",
  "bakinsa": "his mouth",
  "zage": "abuse",
  "ƙarairayi": "lies",
  "barazana": "threat",
  "harshensa": "his language",
  "kwanto": "ambush",
  "ƙauyuka": "villages",
  "kwanton": "ambush",
  "kashe": "kill",
  "kallon": "the look",
  "hannunsa": "his hand",
  "ragargaza": "to destroy",
  "hannu": "hand",
  "fāɗi": "fall",
  "ƙarfinsa": "his strength",
  "ai": "yes",
  "rufe": "cover",
  "fuskarsa": "his face",
  "gani": "see",
  "miyagu": "bad guys",
  "ƙi": "hate",
  "hakki": "the right",
  "ɗaukansu": "take them",
  "danƙa": "grip",
  "taimakon": "the help",
  "marayu": "orphans",
  "karye": "broken",
  "hannun": "the hand",
  "muguntar": "evil",
  "gane": "identify",
  "sarkin": "the king",
  "ƙasarsa": "his country",
  "sha'awar": "desire",
  "ƙarfafa": "consolidate",
  "kukansu": "their cry",
  "kāre": "protect",
  "danne": "suppressed",
  "haddasa": "causing",
  "razana": "fright",
  "samun": "get",
  "yaya": "how",
  "firiya": "first",
  "tsuntsu": "bird",
  "duwatsu": "mountains",
  "duba": "look",
  "bakkunansu": "their mouths",
  "kibiyoyinsu": "their arrows",
  "harbi": "shot",
  "kirki": "integrity",
  "tumɓuke": "uprooted",
  "tushe": "root",
  "adali": "justice",
  "haikalinsa": "his temple",
  "kursiyinsa": "his throne",
  "ya'yan": "sons",
  "idanunsa": "his eyes",
  "ransa": "his soul",
  "son": "love",
  "rikici": "deception",
  "zuba": "pour",
  "garwashin": "coal",
  "zafi": "heat",
  "kibiritu": "sulphur",
  "rabonsu": "their share",
  "taimaka": "help",
  "aminci": "fidelity",
  "ɓace": "vanish",
  "maƙwabcinsa": "his neighbor",
  "zaƙin": "the sweet",
  "maganar": "the word",
  "cike": "full",
  "zukatansu": "their hearts",
  "yanke": "decide",
  "harsunanmu": "our languages",
  "leɓunanmu": "our lips",
  "maigidanmu": "our master",
  "danniyar": "pressure",
  "nishin": "sigh",
  "sharri": "malice",
  "kalmomin": "the words",
  "azurfan": "the silver",
  "tace": "filter",
  "matoyan": "the mats",
  "yumɓu": "plaster",
  "tsabtacce": "clean",
  "sau": "time",
  "tsare": "defend",
  "sake": "again",
  "girmama": "respect",
  "kyau": "excellence",
  "kokawa": "struggle",
  "tunanina": "my thoughts",
  "dube": "look",
  "haske": "light",
  "fuskata": "my face",
  "wawaye": "fools",
  "ransu": "their soul",
  "lalace": "decay",
  "ayyukansu": "their actions",
  "abu": "thing",
  "yan": "that",
  "adam": "adam",
  "akwai": "there is",
  "duka": "beat",
  "kauce": "avoid",
  "lalatattu": "destroyed",
  "cin": "eating",
  "gurasa": "bread",
  "kansu": "themselves",
  "ƙungiyar": "the group",
  "ƙoƙarin": "try",
  "matalauta": "poor",
  "mafakansu": "their refuge",
  "kash": "sorry",
  "isra'ila": "israel",
  "fito": "issue",
  "sa'ar": "luck",
  "mutanensa": "his people",
  "yaƙub": "jacob",
  "wuri": "place",
  "tsarkinka": "your purity",
  "tudunka": "i know",
  "sai": "until",
  "ɓata": "contaminate",
  "baza": "spread",
  "jita": "dish",
  "ɗan'uwansa": "his brother",
  "alkawarinsa": "his promise",
  "zafe": "hot",
  "rance": "loan",
  "karɓan": "the acceptance",
  "hanci": "nose",
  "kā": "why",
  "waɗannan": "these",
  "jijjiguwa": "shaking",
  "miktam": "miktam",
  "shugabana": "my boss",
  "sunan": "the name",
  "gittit": "gone",
  "hannuwanka": "your hands",
  "sararin": "space",
  "faɗa": "say",
  "ake": "ake",
  "haggayiyon": "the combination",
  "sani": "know",
  "girgiza": "shake",
  "ragarsa": "his net",
  "shan": "taking",
  "saurari": "listen",
  "tsarkakan": "the pure",
  "ɗaukakar": "the glory",
  "cikina": "inside me",
  "dangana": "relative",
  "ƙaru": "increase",
  "alloli": "gods",
  "hadayarsu": "their sacrifice",
  "ambaci": "mention",
  "sunayensu": "their names",
  "bakina": "my mouth",
  "rabona": "my share",
  "kwaf": "cup",
  "ɗin": "the",
  "iyakoki": "limits",
  "fāɗo": "fall",
  "wurare": "places",
  "daɗi": "pleasure",
  "ina": "where",
  "gādo": "bed",
  "bansha'awa": "interesting",
  "yabi": "praise",
  "shawara": "advice",
  "koya": "learn",
  "nakan": "i used to",
  "damana": "right",
  "jijjigu": "vibration",
  "harshena": "my language",
  "jikina": "my body",
  "ruɓa": "rot",
  "sanar": "announce",
  "rai": "soul",
  "madawwamin": "eternal",
  "damarka": "your chance",
  "roƙona": "my request",
  "kasa": "fail",
  "kunne": "ear",
  "fitowa": "coming out",
  "leɓuna": "lips",
  "fiffitawata": "my favorite",
  "tă": "facing",
  "idanunka": "your eyes",
  "gwada": "compare",
  "leɓunanka": "your lips",
  "hanyoyin": "the methods",
  "tashin": "the rise",
  "hankali": "mind",
  "sawuna": "my feet",
  "hanyoyinka": "your ways",
  "ƙafafu": "feet",
  "santsi": "smooth",
  "girmar": "size",
  "banmamaki": "miraculous",
  "gābansu": "in front of them",
  "hannunka": "your hand",
  "ido": "eye",
  "inuwar": "the shadow",
  "fikafikanka": "your wings",
  "hari": "attack",
  "tausayi": "pity",
  "bakunansu": "their mouths",
  "shirye": "ready",
  "jefa": "throw",
  "yunwan": "the hunger",
  "abinci": "food",
  "babban": "big",
  "fako": "empty space",
  "maɓuya": "hidden",
  "arangama": "confrontation",
  "durƙusar": "kneeling",
  "takobinka": "your sword",
  "duniyan": "the world",
  "ladarsu": "their reward",
  "rayuwa": "life",
  "so": "love",
  "ya'yansu": "their children",
  "isashe": "enough",
  "wadata": "supply",
  "gamsu": "satisfied",
  "ganin": "to see",
  "kamanninka": "your appearance",
  "waƙa": "song",
  "shawulu": "shawl",
  "ƙarfina": "my strength",
  "cetona": "save me",
  "ƙahon": "the horn",
  "mafakata": "refuge",
  "cancanci": "deserve",
  "kuɓuta": "evade",
  "igiyoyin": "the ropes",
  "shaƙe": "strangle",
  "rigyawan": "the flood",
  "tarkon": "the trap",
  "kukana": "i'm crying",
  "kunnensa": "his ear",
  "rawa": "dance",
  "tussan": "the reason",
  "hayaƙi": "smoke",
  "kafan": "foot",
  "hancinsa": "his nose",
  "ci": "eat",
  "garwashi": "coal",
  "sauko": "come down",
  "baƙaƙen": "black",
  "gizagizai": "overcast",
  "hau": "ascend",
  "kerubobi": "cherubim",
  "shawagi": "fly",
  "fikafikan": "the wings",
  "rufuwarsa": "his death",
  "rumfa": "awning",
  "gizagizan": "the clouds",
  "sarari": "room",
  "kasancewarsa": "his presence",
  "ƙanƙara": "hail",
  "walƙiya": "flash",
  "tsawa": "thunder",
  "kāra": "cane",
  "harba": "shoot",
  "watsar": "discard",
  "fafare": "fare",
  "kwarin": "the valley",
  "fili": "field",
  "numfasa": "breathe",
  "hancinka": "your nose",
  "fi": "exceed",
  "masifa": "disaster",
  "taimakona": "my help",
  "fitar": "out",
  "daɗina": "my taste",
  "lada": "reward",
  "ban": "ban",
  "juyewa": "upside down",
  "dokokinsa": "his laws",
  "juye": "divert",
  "ƙa'idodinsa": "its principles",
  "gabansa": "before him",
  "tsabta": "clarity",
  "karkatacce": "twisted",
  "fitilata": "my lamp",
  "taimakonka": "your help",
  "runduna": "company",
  "rinjayi": "influenced",
  "katanga": "wall",
  "hanyarsa": "his way",
  "cikakkiya": "complete",
  "allahnmu": "our god",
  "hanyarta": "her way",
  "ƙafafuna": "my feet",
  "ƙafafun": "wheels",
  "barewa": "deer",
  "ƙwanƙoli": "the collar",
  "horar": "training",
  "yaƙi": "war",
  "bakan": "spectrum",
  "tagulla": "copper",
  "garkuwar": "shield",
  "riƙe": "hold",
  "sunkuya": "bow down",
  "fadada": "amplify",
  "ƙarƙashina": "under me",
  "ɗiɗɗigena": "my fingers",
  "rusuna": "i bow down",
  "murƙushe": "crushed",
  "laushi": "soft",
  "zubar": "shed",
  "tituna": "streets",
  "harin": "attack",
  "bayina": "my servants",
  "zarar": "once",
  "biyayya": "obedience",
  "baƙi": "black",
  "karai": "just",
  "rawan": "the dance",
  "sāka": "release",
  "ana": "here",
  "tā": "facing",
  "sarkinsa": "his king",
  "zuriyarsa": "his descendants",
  "hannuwansa": "his hands",
  "jawabi": "speech",
  "kalmar": "the word",
  "hurta": "relax",
  "amon": "amon",
  "muryarsu": "their voice",
  "kaiwa": "reach",
  "kalmominsu": "their words",
  "tenti": "tent",
  "ango": "fiancé",
  "rumfarsa": "his shed",
  "gwani": "expert",
  "tsere": "race",
  "taso": "rise",
  "wancan": "that",
  "ɓuya": "hide",
  "zafinta": "her pain",
  "wartsakar": "refreshing",
  "farillan": "the ordinances",
  "hikima": "wisdom",
  "ƙa'idodin": "the rules",
  "idanu": "eyes",
  "tabbatattu": "sure",
  "zinariya": "gold",
  "daraja": "worth",
  "fiye": "more",
  "zalla": "pure",
  "zuma": "honey",
  "zaƙi": "sweetness",
  "kaki": "you",
  "wurinsu": "their place",
  "gargaɗe": "warning",
  "bawanka": "your servant",
  "rabe": "recognize",
  "kurakuransa": "his mistakes",
  "gafarta": "forgive",
  "ɓoyayyun": "hidden",
  "laifofinsa": "his crimes",
  "zunubin": "the sin",
  "ganganci": "deliberate",
  "tunanin": "think",
  "gamsuwa": "satisfaction",
  "fansata": "redemption",
  "aiko": "send",
  "gudummawa": "donation",
  "sadakokinka": "your gifts",
  "hadayunka": "your offerings",
  "biya": "payment",
  "bukatan": "the need",
  "ranka": "your soul",
  "sowa": "sowa",
  "tutotinmu": "our flag",
  "bukatunka": "your needs",
  "samansa": "the top of it",
  "ikon": "power",
  "damansa": "his right",
  "kekunan": "the bikes",
  "dawakai": "horses",
  "mun": "we",
  "daram": "right",
  "muka": "we",
  "ƙarfinka": "your strength",
  "cikinsa": "inside him",
  "ƙwarai": "very",
  "nasarorin": "the achievements",
  "bukatar": "the need",
  "hana": "forbid",
  "roƙon": "the request",
  "leɓunansa": "his lips",
  "marabce": "welcome",
  "yalwar": "abundance",
  "albarka": "blessing",
  "rawanin": "the crown",
  "zallan": "purely",
  "tsawo": "length",
  "kwanaki": "days",
  "ɗaukakarsa": "his glory",
  "mayar": "return",
  "kasancewarka": "your presence",
  "ƙauna": "love",
  "kakkama": "i'm sorry",
  "ƙinka": "hate you",
  "lokacin": "the time",
  "bayyanarka": "your appearance",
  "wutar": "the fire",
  "matoya": "fan",
  "haɗiye": "swallow",
  "wutarsa": "his fire",
  "cinye": "eat",
  "zuriyarsu": "their descendants",
  "ƙirƙiro": "creative",
  "mugayen": "the bad ones",
  "dabaru": "logic",
  "auna": "measure",
  "ikonka": "your power",
  "salon": "salon",
  "matar": "the woman",
  "zomon": "the rabbit",
  "safiya": "morning",
  "nisa": "distance",
  "nishina": "my sigh",
  "tsarkin": "purity",
  "yabon": "praise",
  "kakanninmu": "our ancestors",
  "bege": "longing",
  "dai": "that's right",
  "tsutsa": "larva",
  "rena": "rena",
  "gan": "see",
  "ashar": "ten",
  "kaɗa": "wave",
  "daɗinsa": "enjoy it",
  "ƙirjin": "the chest",
  "mahaifiyata": "my mother",
  "bijimai": "bulls",
  "bashan": "debt",
  "tsaka": "between",
  "zakoki": "lions",
  "ruri": "stimulation",
  "fiffito": "priority",
  "mahaɗai": "mixer",
  "narke": "melt",
  "bushe": "dry",
  "kasko": "pot",
  "manne": "glue",
  "dasashina": "my transplant",
  "kwantar": "calm down",
  "ƙurar": "the dust",
  "karnuka": "dogs",
  "soki": "criticize",
  "rigunana": "my clothes",
  "tsakaninsu": "among them",
  "sauri": "speed",
  "taimake": "help",
  "ceci": "save",
  "takobi": "sword",
  "bakin": "mouth",
  "ƙahonin": "the horns",
  "yan'uwana": "my brothers",
  "sujada": "worship",
  "zuriyar": "offspring",
  "wahalar": "the difficulty",
  "wuya": "neck",
  "kukansa": "his cry",
  "yabona": "i see",
  "gaban": "ahead",
  "tsoronka": "your fear",
  "alkawarina": "my promise",
  "ƙoshi": "full",
  "rayu": "live",
  "iyalan": "the family",
  "attajiran": "the rich",
  "gangara": "slope",
  "zuriya": "seed",
  "hidima": "service",
  "haifa": "reproduce",
  "kiwona": "raise me",
  "makiyaya": "meadow",
  "ciyawa": "grass",
  "hayaniya": "clutter",
  "tafiya": "walk",
  "kwari": "valley",
  "bulalarka": "your whip",
  "dūka": "beat",
  "sandanka": "your stick",
  "ta'aziyya": "comfort",
  "tebur": "table",
  "kwanakin": "the days",
  "gidan": "the house",
  "cikinta": "inside her",
  "gina": "build",
  "hawan": "the ride",
  "tudun": "the hill",
  "wurinsa": "his place",
  "gunki": "idol",
  "rantse": "swear",
  "fiffitawa": "preference",
  "cetonsa": "his salvation",
  "tsaran": "generation",
  "nemansa": "looking for him",
  "kawunanku": "your heads",
  "ƙofofi": "doors",
  "ɗagu": "raise",
  "daɗaɗɗun": "ancient",
  "iko": "power",
  "maɗaukaki": "the highest",
  "tayarwa": "raising",
  "dalili": "reason",
  "gaskiyarka": "your truth",
  "begena": "my hope",
  "yini": "a day",
  "tun": "since",
  "dā": "and",
  "zunuban": "sins",
  "ƙuruciyata": "my childhood",
  "tawayena": "my rebellion",
  "nagari": "good",
  "koyar": "to teach",
  "tawali'u": "humility",
  "ƙaunatattu": "loved ones",
  "alkawari": "promise",
  "bukaci": "need",
  "laifina": "my fault",
  "kwanakinsa": "his days",
  "wadace": "enough",
  "gāji": "tired",
  "amince": "ensure",
  "tsoronsa": "his fear",
  "tarko": "trap",
  "wurina": "my place",
  "kaɗaice": "loneliness",
  "damuwoyin": "the worries",
  "ninka": "fold",
  "azabata": "my torment",
  "ɗauke": "carry",
  "zunubaina": "my sins",
  "ƙina": "i hate it",
  "mutunci": "dignity",
  "fanshi": "redemption",
  "wahalarsu": "their suffering",
  "rashin": "lack",
  "zargi": "criticism",
  "kaucewa": "avoidance",
  "jarraba": "test",
  "tarayya": "communion",
  "riya": "tempt",
  "jinin": "the blood",
  "wanke": "wash",
  "bagadenka": "your altar",
  "ayyukanka": "your actions",
  "haskena": "my light",
  "mafakar": "the shelter",
  "tasar": "dish",
  "maƙiyina": "my enemy",
  "mayaƙa": "fighters",
  "roƙi": "request",
  "nema": "seek",
  "kyan": "beautiful",
  "zamansa": "his stay",
  "tabanakul": "tabanakul",
  "nasa": "his",
  "hadaya": "sacrifice",
  "mahaifina": "my father",
  "karɓe": "accept",
  "miƙaƙƙiyar": "the offer",
  "hanya": "way",
  "shaidar": "the evidence",
  "ƙarfin": "the strength",
  "gwiwa": "knee",
  "hali": "conduct",
  "kunnen": "the ear",
  "ƙashi": "bone",
  "yayinda": "while",
  "wajen": "outside",
  "maƙwabtansu": "their neighbors",
  "aikinsu": "their work",
  "kula": "care",
  "tsalle": "jump",
  "godiya": "gratitude",
  "kagarar": "the fortress",
  "albarkace": "blessing",
  "kiwonsu": "raising them",
  "manya": "adults",
  "tsarkinsa": "his purity",
  "itatuwan": "the trees",
  "al'ul": "cedar",
  "lebanon": "the lips",
  "dutsen": "the mountain",
  "maraƙi": "calf",
  "siriyon": "sirion",
  "walƙatar": "the wretched",
  "hamadan": "the desert",
  "murɗa": "twist",
  "oak": "oak",
  "kakkaɓe": "fight",
  "kurmi": "forest",
  "rigyawa": "flood",
  "zurfafa": "deep",
  "dawo": "return",
  "gangarawa": "going down",
  "tsarkakansa": "his saints",
  "alherinsa": "his kindness",
  "matuƙa": "limit",
  "yiwuwa": "credibility",
  "katangar": "the castle",
  "wace": "which",
  "hallakata": "destroy me",
  "amincinka": "your faithfulness",
  "tuɓe": "undress",
  "rigar": "the dress",
  "makokina": "my mourning",
  "rahamarka": "your mercy",
  "kunnenka": "your ear",
  "jagorance": "guide",
  "gumakan": "the idols",
  "tafke": "leak",
  "tilis": "tilis",
  "shekaruna": "my age",
  "azaba": "torment",
  "tamƙar": "like",
  "maƙwabtana": "my neighbors",
  "abokaina": "my friends",
  "titi": "street",
  "fasasshen": "cracked",
  "raɗe": "whispered",
  "raɗen": "the whisper",
  "maƙarƙashiya": "constipation",
  "lokutana": "my times",
  "fafara": "fara",
  "ƙarairayinsu": "their lies",
  "alherinka": "your kindness",
  "zamanka": "your life",
  "harsuna": "languages",
  "zagi": "insult",
  "ƙaunarsa": "his love",
  "birni": "city",
  "tsorona": "my fear",
  "adana": "save",
  "amintattu": "trusted",
  "cikakke": "whole",
  "maskil": "mask",
  "zunubansa": "his sins",
  "lissafin": "list",
  "zunubinsa": "his sin",
  "ruhunsa": "his spirit",
  "nauyi": "weight",
  "shanye": "absorb",
  "ƙaf": "foot",
  "zunubina": "my sin",
  "laifofina": "my crimes",
  "laifin": "the crime",
  "ɓuyata": "hide",
  "waƙoƙin": "the songs",
  "umarce": "command",
  "doki": "horse",
  "azanci": "sensibility",
  "dole": "must",
  "linzami": "mouse",
  "ragama": "bit",
  "azaban": "the punishment",
  "zuciyarku": "your heart",
  "garaya": "harp",
  "molo": "hello",
  "sabuwar": "the new one",
  "gwaninta": "skill",
  "rundunar": "the army",
  "taurarinsu": "their stars",
  "numfashin": "the breath",
  "tattara": "concentrate",
  "tuluna": "jar",
  "gidajen": "the houses",
  "ajiya": "storage",
  "soke": "frustrate",
  "shiryen": "the plans",
  "wofintar": "empty",
  "manufofin": "the policy",
  "zamanai": "ages",
  "al'ummar": "the community",
  "yeahohnta": "yeah",
  "gādonsa": "his legacy",
  "mazauninsa": "his residence",
  "zukatan": "the hearts",
  "mayaƙansa": "his warriors",
  "idanun": "the eyes",
  "yunwa": "famine",
  "muna": "we are",
  "jiran": "waiting",
  "taimakonmu": "our help",
  "garkuwarmu": "our shield",
  "zukatanmu": "our hearts",
  "begenmu": "our hope",
  "haukace": "crazy",
  "abimelek": "abimelech",
  "kullayaumi": "everyday",
  "yabonsa": "his praise",
  "leɓunana": "my lips",
  "dubansa": "look at him",
  "fuskokinsu": "their faces",
  "rufuwa": "cover up",
  "matalauci": "poor",
  "wahalarsa": "his suffering",
  "mala'ikan": "the angel",
  "sansani": "camp",
  "ya'yana": "my brothers",
  "muku": "to you",
  "waninku": "other than you",
  "harshenka": "your language",
  "leɓunanku": "your lips",
  "faɗar": "say",
  "samunta": "get it",
  "kunnuwansa": "his ears",
  "sauraran": "listening",
  "fuskar": "the face",
  "ruhu": "spirit",
  "dukansu": "all of them",
  "ƙasusuwansa": "his bones",
  "ɗayansu": "one of them",
  "gāban": "ahead",
  "bayinsa": "his servants",
  "hamayya": "opposition",
  "makami": "weapon",
  "māshi": "spear",
  "fafarata": "my face",
  "kunyatar": "shame",
  "lalacewata": "my destruction",
  "ruɗe": "confused",
  "korarsu": "expel them",
  "hanyarsu": "their way",
  "fafararsu": "their penis",
  "domina": "for me",
  "zato": "guess",
  "lalacinsu": "their corruption",
  "ƙarfinsu": "their strength",
  "fashi": "robbery",
  "shaidu": "witnesses",
  "imani": "belief",
  "nadama": "regret",
  "makoki": "mourning",
  "azumi": "fast",
  "addu'o'i": "prayers",
  "abokina": "my friend",
  "ɗan'uwana": "my brother",
  "sunkuyar": "bow down",
  "tsagaitawa": "stop",
  "riyar": "riyar",
  "hararata": "hararat",
  "ƙiyayya": "hatred",
  "farmakinsu": "their attack",
  "ɗumbun": "the bush",
  "maƙaryatan": "liars",
  "zagen": "abuse",
  "wage": "away",
  "idanunmu": "our eyes",
  "wulaƙanci": "humiliation",
  "nasarata": "my success",
  "riƙa": "continue",
  "lafiyar": "health",
  "bawansa": "his servant",
  "zancen": "the conversation",
  "daina": "cease",
  "gadonsa": "his bed",
  "hukuncinka": "your judgment",
  "zurfi": "depth",
  "dabba": "animal",
  "misalin": "the example",
  "ƙanana": "small",
  "rafin": "the stream",
  "maɓulɓular": "the source",
  "haskenka": "your light",
  "mukan": "we",
  "gaskiyar": "the truth",
  "ƙafar": "the foot",
  "zube": "spill",
  "tsorata": "scare",
  "kishin": "jealousy",
  "ɗanyun": "raw",
  "ganyaye": "leaves",
  "more": "more",
  "daɗinka": "your pleasure",
  "bukatun": "the requirements",
  "zuciyarka": "your heart",
  "natsu": "calm down",
  "haƙuri": "patience",
  "hanyoyinsu": "their ways",
  "shiryensu": "their readiness",
  "hasala": "hasla",
  "datse": "cut off",
  "ƙanƙanen": "small",
  "shuɗe": "blue",
  "same": "same",
  "cikakkiyar": "perfect",
  "ciji": "bite",
  "dariyar": "the laugh",
  "ranarsu": "their day",
  "zare": "thread",
  "baka": "you're not",
  "takubansu": "their swords",
  "kakkarye": "strong",
  "arzikin": "the wealth",
  "zarge": "accuse",
  "sane": "aware",
  "gādonsu": "their inheritance",
  "dawwama": "forever",
  "masifu": "disaster",
  "yanƙwane": "cut",
  "yalwace": "plenty",
  "gonaki": "farms",
  "bayar": "pay",
  "la'anta": "curse",
  "sawu": "trail",
  "kahu": "what",
  "yaro": "child",
  "tsufa": "antiquity",
  "burodi": "bread",
  "bashi": "debt",
  "amintattunsa": "his trust",
  "allahnsa": "his god",
  "ƙoƙari": "attempt",
  "ikonsu": "their power",
  "gādon": "the inheritance",
  "kawar": "get rid of",
  "azzalumi": "oppressor",
  "yaɗuwa": "spreading",
  "ɗanyen": "raw",
  "kasancewa": "attendance",
  "roƙo": "application",
  "kibiyoyinka": "your arrows",
  "nauyin": "the burden",
  "ɗauka": "take",
  "miyakuna": "the poor",
  "ruɓe": "decay",
  "wari": "smell",
  "wawancina": "my stupidity",
  "bayana": "my background",
  "fama": "struggle",
  "zazzaɓi": "fever",
  "sharkaf": "shark",
  "bukatata": "my need",
  "shimfiɗe": "layout",
  "ɓoyuwa": "hidden",
  "bugu": "printing",
  "ƙare": "accomplish",
  "rabu": "break up",
  "guje": "run away",
  "tarkonsu": "their trap",
  "cuce": "hurt",
  "zance": "reference",
  "lalatar": "the destruction",
  "sukutum": "sukum",
  "kurma": "deaf",
  "bebe": "dumb",
  "kirari": "cry",
  "ƙafata": "my foot",
  "gab": "gab",
  "fāɗuwa": "decline",
  "damu": "worry",
  "kina": "you are",
  "alherina": "my grace",
  "zarafina": "my opportunity",
  "yedutun": "the eyes",
  "hanyoyina": "my ways",
  "muddin": "as long as",
  "ƙaruwa": "exaggeration",
  "rayuwata": "my life",
  "kwanakina": "my days",
  "wucewa": "passage",
  "tafin": "sole",
  "ran": "soul",
  "tsammani": "guess",
  "kāriya": "bitch",
  "shirim": "shit",
  "komowa": "return",
  "tara": "nine",
  "dukiya": "property",
  "sanin": "to know",
  "bugun": "beat",
  "zunubinsu": "their sin",
  "wadatarsu": "their prosperity",
  "asu": "moth",
  "kurmance": "deaf",
  "kakannina": "my grandparents",
  "kau": "go away",
  "taɓo": "mud",
  "tsayayyen": "stable",
  "waƙar": "the song",
  "dogararsa": "his trust",
  "banmamakin": "the miracle",
  "faɗe": "sandal",
  "wuce": "expire",
  "sadaka": "charity",
  "sha'awa": "interest",
  "kunnuwana": "my ears",
  "huda": "pierce",
  "rubuce": "writing",
  "littafi": "book",
  "nufinka": "your will",
  "jama'arka": "your people",
  "gashin": "the hair",
  "fid": "fid",
  "rikice": "confused",
  "mamaki": "astonishment",
  "kunyar": "shame",
  "jinkirta": "delay",
  "tausayin": "the sympathy",
  "maƙiyansa": "his enemies",
  "gadon": "the bed",
  "lafiyarsa": "his health",
  "ciwon": "the pain",
  "muguwar": "the evil one",
  "ganina": "see me",
  "tattare": "gathered",
  "zarafi": "opportunity",
  "fita": "exit",
  "bazawa": "publication",
  "raɗa": "whisper",
  "fata": "skin",
  "kwanciya": "bedding",
  "kurkusa": "close",
  "kora": "expel",
  "maza": "men",
  "marmarin": "longing",
  "rafuffuka": "streams",
  "marmarinka": "your desire",
  "ƙishin": "hate",
  "sadu": "meet",
  "hawayena": "my tears",
  "abincina": "my food",
  "allahnka": "your god",
  "jama'a": "society",
  "bishe": "go",
  "jere": "row",
  "urdun": "urdu",
  "ƙwanƙolin": "the crown",
  "hermon": "hermon",
  "mizar": "mizar",
  "rurin": "roar",
  "matsirgar": "matsirgar",
  "ruwanka": "your water",
  "raƙuma": "camels",
  "igiyoyi": "ropes",
  "waƙarsa": "his song",
  "maƙiyana": "my enemies",
  "hakkina": "my right",
  "dutsenka": "your mountain",
  "bagaden": "the altar",
  "murnata": "my joy",
  "kunnuwanmu": "our ears",
  "kwanakinsu": "their days",
  "kori": "fired",
  "dasa": "plant",
  "haɓaka": "increase",
  "takobinsu": "their swords",
  "hannunsu": "their hands",
  "damanka": "your right",
  "ƙaunace": "love",
  "tura": "push",
  "maƙiyanmu": "our enemies",
  "bakana": "my bow",
  "takobina": "my sword",
  "fariyarmu": "our pride",
  "mayaƙanmu": "our warriors",
  "sayar": "sell",
  "kuɗin": "the money",
  "taka": "step",
  "maƙwabtanmu": "our neighbors",
  "rufu": "cover",
  "ba'ar": "mocking",
  "alwashi": "vow",
  "ramuwa": "compensation",
  "faru": "happen",
  "alkawarinka": "your promise",
  "ƙafafunmu": "our feet",
  "maishe": "what is it",
  "farautar": "hunting",
  "karnukan": "the dogs",
  "ƙirin": "krin",
  "hannuwanmu": "our hands",
  "asiran": "the secret",
  "tumakin": "the sheep",
  "yanka": "amputate",
  "azabanmu": "our torment",
  "jikunanmu": "our bodies",
  "lili": "lily",
  "aure": "marriage",
  "kyakkyawan": "beautiful",
  "ayoyina": "my verses",
  "alƙalamin": "the pen",
  "ƙwararren": "the expert",
  "marubuci": "writer",
  "gefenka": "your side",
  "jarumi": "warrior",
  "madadin": "alternative",
  "tsini": "point",
  "ƙafafunka": "your feet",
  "kursiyinka": "your throne",
  "sandar": "the stick",
  "mulkinka": "your kingdom",
  "abokanka": "your friends",
  "man": "man",
  "rigunanka": "your clothes",
  "ƙanshin": "the aroma",
  "turaren": "perfume",
  "mur": "myrrh",
  "aloyes": "alloys",
  "kashiya": "cashier",
  "fadan": "fight",
  "ado": "decoration",
  "hauren": "go up",
  "giwa": "elephant",
  "kaɗen": "the rhythm",
  "matan": "the women",
  "amarya": "bride",
  "sarauniya": "queen",
  "saye": "acquisition",
  "ofir": "ophir",
  "ki": "yes",
  "saurara": "listen",
  "diya": "daughter",
  "mutanenki": "your people",
  "mahaifinki": "your father",
  "kyanki": "your beauty",
  "maigidanki": "your boss",
  "diyar": "the daughter",
  "taya": "boot",
  "mawadata": "rich",
  "tagomashinki": "your favor",
  "gimbiya": "princess",
  "fada": "palace",
  "kyakkyawa": "lovely",
  "saƙa": "knit",
  "rigarta": "her dress",
  "zaren": "thread",
  "riguna": "dresses",
  "abokanta": "her friends",
  "budurwai": "girlfriends",
  "biye": "followed",
  "ya'yanka": "your children",
  "kakanninka": "your ancestors",
  "fāɗin": "the fall",
  "alamot": "symptoms",
  "mafakarmu": "our refuge",
  "ƙarfinmu": "our strength",
  "ruwansa": "his water",
  "kumfa": "foam",
  "tumbatsansu": "their relationship",
  "kogi": "river",
  "tsattsarkan": "the holy",
  "mulkoki": "kingdoms",
  "muryarsa": "his voice",
  "kagararmu": "our fortress",
  "kangon": "the ruins",
  "yaƙoƙi": "wars",
  "tsit": "quiet",
  "bakkuna": "mouths",
  "māsu": "theirs",
  "garkuwoyi": "shields",
  "tafa": "clap",
  "hannuwanku": "your hands",
  "muryoyin": "the voices",
  "ƙarƙashinmu": "under us",
  "zaɓar": "select",
  "gādonmu": "our heritage",
  "abar": "abar",
  "taƙamar": "pride",
  "haura": "go up",
  "ƙarar": "volume",
  "ƙahoni": "horns",
  "sarkinmu": "our king",
  "ibrahim": "abraham",
  "sarkunan": "the kings",
  "mafificin": "the best",
  "tsayinta": "its length",
  "tsayi": "stop",
  "zafon": "the heat",
  "fadodinta": "her palace",
  "rundunoni": "forces",
  "mace": "woman",
  "naƙuda": "labor",
  "jiragen": "the planes",
  "tarshish": "tarshish",
  "iskar": "the wind",
  "ƙauyukan": "the villages",
  "yahuda": "jew",
  "hukuntanka": "punish you",
  "hasumiyoyinta": "its towers",
  "katangarta": "her castle",
  "tsara": "arrange",
  "jagorarmu": "our guide",
  "ƙarshe": "end",
  "babba": "great",
  "arziki": "wealth",
  "ganewa": "identification",
  "kunnena": "my ear",
  "karin": "more",
  "kacici": "riddle",
  "kacicina": "my circumcision",
  "arzikinsu": "their wealth",
  "tsada": "cost",
  "isa": "enough",
  "shigan": "enter",
  "kaburburansu": "their graves",
  "gidajensu": "their houses",
  "filaye": "lands",
  "sunayen": "the names",
  "arzikinsa": "his fortune",
  "dabbobi": "animals",
  "ƙaddarar": "the determination",
  "mabiyansu": "their followers",
  "tabbatar": "confirm",
  "faɗinsu": "their width",
  "ƙaddara": "destiny",
  "abincin": "the food",
  "kamanninsu": "their appearance",
  "darajar": "value",
  "gidansa": "his house",
  "darajarsa": "his value",
  "raye": "live",
  "gamu": "meet",
  "tsarar": "generation",
  "kakanninsa": "his ancestors",
  "asaf": "asaf",
  "fitowar": "the output",
  "haskakawa": "shine",
  "cinyewa": "to consume",
  "shafaffuna": "anoint me",
  "mutanena": "my people",
  "shaida": "witness",
  "allahnku": "your god",
  "hadayunku": "your offerings",
  "bijimi": "bull",
  "turkenku": "your turkey",
  "awaki": "goats",
  "garkunanku": "your herds",
  "dabbar": "the animal",
  "dubban": "thousands",
  "tuddai": "hills",
  "tsuntsun": "the bird",
  "halittun": "the creatures",
  "duniyar": "the world",
  "hadayar": "the offering",
  "alkawuranku": "your promises",
  "dokokina": "my rules",
  "kun": "you",
  "umarnina": "my instructions",
  "bayanku": "after you",
  "ɓarawo": "thief",
  "mazinata": "adulterer",
  "bakunanku": "your mouths",
  "gyara": "repair",
  "ɗan'uwanku": "your brother",
  "mahaifinku": "your father",
  "fuskarku": "your face",
  "natan": "natan",
  "zina": "adultery",
  "batsheba": "bathsheba",
  "tausayinka": "your pity",
  "tsarkake": "sanctify",
  "idonka": "your eyes",
  "sassan": "the sections",
  "hizzob": "hizb",
  "tsab": "tsab",
  "dusan": "dusan",
  "fari": "drought",
  "ƙasusuwan": "the bones",
  "halitta": "create",
  "sabunta": "renew",
  "ruhunka": "your spirit",
  "ruhun": "the spirit",
  "komo": "come back",
  "karyayyen": "broken",
  "karyayyiya": "lie",
  "urushalima": "jerusalem",
  "hadayu": "offerings",
  "ɗungum": "dungum",
  "faranta": "happy",
  "doyeg": "doyeg",
  "edom": "edom",
  "ahimelek": "ahimelech",
  "reza": "razor",
  "maimakon": "instead of",
  "cutarwa": "harm",
  "fizge": "twitch",
  "tentinka": "your tent",
  "mafakarsa": "his refuge",
  "zaitun": "olive",
  "tsarkakanka": "your purity",
  "mahalat": "necessary",
  "wawa": "fool",
  "fa": "fa",
  "firgita": "panic",
  "ƙinsa": "hate it",
  "arzuta": "wealth",
  "zifawa": "sweating",
  "cikinmu": "inside us",
  "yardar": "consent",
  "wahalolina": "my difficulties",
  "damuna": "i'm worried",
  "hankalina": "my mind",
  "surutan": "the noise",
  "jawo": "draw",
  "haushina": "my anger",
  "tsorace": "scared",
  "tsoracen": "scared",
  "kurciya": "dove",
  "hanzarta": "accelerate",
  "hadiri": "thunderstorm",
  "rikitar": "confusion",
  "birkitar": "brake",
  "maganarsu": "their words",
  "titunanta": "its streets",
  "zagina": "insult me",
  "jure": "endure",
  "maƙiyi": "the enemy",
  "zumunci": "relationship",
  "labari": "story",
  "masauƙi": "accommodation",
  "cikinsu": "among them",
  "fisshe": "piss off",
  "azabtar": "torture",
  "canja": "commute",
  "abokansa": "his friends",
  "maganarsa": "his words",
  "kalmominsa": "his words",
  "sulɓi": "bald",
  "takuba": "swords",
  "zārarru": "special",
  "damuwoyinku": "your worries",
  "lalacewa": "damage",
  "rabin": "half",
  "rayuwarsu": "their lives",
  "murya": "voice",
  "filistiyawa": "philistines",
  "gat": "gat",
  "matsa": "clamp",
  "harinsu": "their attack",
  "sunana": "my name",
  "bina": "follow me",
  "fariyarsu": "their pride",
  "maganata": "my words",
  "takawata": "my piety",
  "sam": "sam",
  "kuɓuce": "elude",
  "saukar": "down",
  "lissafta": "calculate",
  "littafinka": "your book",
  "hadayuna": "my sacrifices",
  "kogo": "cave",
  "masifar": "disaster",
  "manufarsa": "his purpose",
  "aika": "send",
  "amincinsa": "his safety",
  "kwance": "unscrew",
  "haƙoransu": "their teeth",
  "kibiyoyi": "arrows",
  "kaifi": "sharp",
  "shimfiɗa": "spread",
  "raga": "net",
  "hanyata": "my way",
  "hargitsi": "turmoil",
  "maƙaryata": "liar",
  "dafinsu": "their poison",
  "dafin": "poison",
  "maciji": "snake",
  "gamsheƙan": "perfect",
  "toshe": "plug",
  "gardi": "guard",
  "dabarar": "the trick",
  "gwanin": "the expert",
  "fiƙoƙin": "the wings",
  "bakansu": "their bow",
  "murtsuke": "crush",
  "katantanwun": "snails",
  "narkewa": "digestion",
  "jinjirin": "the crescent moon",
  "matacce": "dead",
  "tukwanenka": "your pots",
  "ƙayayyuwa": "thorny",
  "busasshe": "dry",
  "rama": "compensate",
  "tsaron": "the defense",
  "jirana": "waiting for me",
  "halin": "the situation",
  "maciya": "snake",
  "amana": "belief",
  "haƙora": "teeth",
  "tofawa": "to spit",
  "tofar": "spit",
  "leɓunansu": "their lips",
  "ƙaunata": "love",
  "barkatai": "i'm sorry",
  "maganganun": "the statements",
  "ƙarairayin": "lies",
  "sarai": "completely",
  "iyakar": "the limit",
  "haushi": "anger",
  "lilin": "linen",
  "koyarwa": "tuition",
  "aram": "aram",
  "naharayim": "naharaim",
  "zoba": "overlap",
  "yowab": "joab",
  "gishiri": "salt",
  "fashe": "break",
  "kāriyarmu": "our defense",
  "tsaga": "split",
  "daure": "endure",
  "karayarta": "her fracture",
  "inabin": "grapes",
  "tuta": "flag",
  "rarraba": "alienate",
  "shekem": "shekem",
  "sukkot": "sukkot",
  "gileyad": "gilead",
  "manasse": "manasseh",
  "efraim": "ephraim",
  "hular": "hat",
  "kwanona": "my bowl",
  "mulkina": "my kingdom",
  "mowab": "moab",
  "kwanon": "the bowl",
  "wankina": "my laundry",
  "takalmina": "my shoes",
  "filistiya": "philistia",
  "kirarin": "call",
  "hasumiya": "tower",
  "marmari": "desire",
  "shekarunsa": "his age",
  "zaburar": "the psalm",
  "hutu": "rest",
  "jinganannen": "carefully",
  "bango": "wall",
  "rusasshen": "destroyed",
  "kintsa": "pack",
  "matsayinsa": "his position",
  "martaba": "dignity",
  "zuciyarsu": "their heart",
  "la'antawa": "to curse",
  "dogarata": "my trust",
  "girmata": "my size",
  "lokuta": "times",
  "attajirai": "the rich",
  "ma'auni": "balance",
  "ƙwace": "snatch",
  "sata": "steal",
  "arzikinku": "your fortune",
  "hamadar": "the desert",
  "nacewa": "persistence",
  "ƙishinka": "hate you",
  "busasshiyar": "dry",
  "zozaye": "zozaye",
  "tunaninka": "your thoughts",
  "zurfafan": "deep",
  "bakunan": "the mouths",
  "barazanan": "the threat",
  "dauren": "the bond",
  "wāsa": "game",
  "harsunansu": "their languages",
  "juna": "each other",
  "ƙullensu": "their locks",
  "tarkunansu": "their traps",
  "wuyar": "hard",
  "harbe": "shot",
  "alkawuranmu": "our promises",
  "zunubai": "sins",
  "laifofinmu": "our crimes",
  "filayenka": "your fields",
  "ayyuka": "actions",
  "cetonmu": "our salvation",
  "begen": "hope",
  "raƙumansu": "their waves",
  "tumbatsar": "tumbatsar",
  "banruwa": "banruwa",
  "azurta": "supply",
  "hatsi": "grain",
  "kwarara": "pour",
  "baje": "spread",
  "kunyoyinta": "her shame",
  "yayyafi": "sprinkle",
  "tsire": "plant",
  "tsirenta": "her plants",
  "kaka": "autumn",
  "amalankenka": "your deeds",
  "makiyayan": "the shepherds",
  "dausayin": "the wetland",
  "kiwo": "breeding",
  "garkuna": "herds",
  "ayyukansa": "his actions",
  "ƙafa": "foot",
  "ikonsa": "his power",
  "rayukanmu": "our souls",
  "azurfa": "silver",
  "kurkuku": "prison",
  "jibga": "jibga",
  "kaya": "load",
  "bayanmu": "after us",
  "kawunanmu": "our heads",
  "yalwa": "abundance",
  "alkawurana": "my promises",
  "alkawuran": "the promises",
  "kitsen": "fat",
  "baye": "bae",
  "raguna": "lambs",
  "janye": "arouse",
  "girbinta": "her harvest",
  "hura": "hura",
  "hawa": "hoist",
  "uba": "father",
  "gwauraye": "widows",
  "kaɗaici": "loneliness",
  "iyalai": "families",
  "waƙoƙi": "songs",
  "wofi": "empty",
  "sinai": "sinai",
  "rayar": "live",
  "yalwarka": "your abundance",
  "tanada": "she has",
  "umarni": "instructions",
  "shelarsa": "his announcement",
  "gaggauce": "rush",
  "ganima": "trophy",
  "garken": "the flock",
  "dalaye": "reasons",
  "fikafikanta": "her wings",
  "ƙyalli": "shine",
  "zalmon": "cruelty",
  "duwatsun": "the mountains",
  "alfarma": "pride",
  "kishi": "jealousy",
  "wuyan": "the neck",
  "karusan": "the carriage",
  "ninkin": "double",
  "tawagarka": "your team",
  "kyautai": "gifts",
  "nauyinmu": "our responsibility",
  "kawunan": "the heads",
  "gashi": "hair",
  "ƙafafunku": "your feet",
  "maƙiyanku": "your enemies",
  "harsunan": "the languages",
  "gwanonka": "your good",
  "bayyane": "obvious",
  "gwanon": "the good",
  "mawaƙa": "singer",
  "makaɗa": "orchestra",
  "bugan": "printed",
  "ganguna": "drums",
  "ƙaramar": "the little one",
  "kabilar": "the tribe",
  "babbar": "big",
  "ƙungiya": "association",
  "zebulun": "zebulun",
  "naftali": "naphthalene",
  "jejin": "the desert",
  "kyauro": "beauty",
  "maruƙan": "the calves",
  "jakadu": "ambassadors",
  "masar": "egypt",
  "kanta": "counter",
  "masarautan": "the kingdom",
  "daɗaɗɗen": "ancient",
  "wuyata": "my neck",
  "nutse": "sink",
  "maƙogwarona": "my throat",
  "dushe": "dim",
  "tilasta": "coerce",
  "wautata": "my stupidity",
  "jimre": "endure",
  "bare": "stranger",
  "himma": "initiative",
  "ƙunata": "burn",
  "zaginka": "insult you",
  "rigunan": "the dress",
  "ƙofa": "door",
  "bugaggu": "printed",
  "giya": "beer",
  "tabbacin": "confirmation",
  "fanshe": "redemption",
  "mataimaki": "assistant",
  "ɗaci": "bitter",
  "inabi": "grapes",
  "tsami": "sour",
  "ƙishi": "envy",
  "teburin": "the table",
  "gabansu": "before them",
  "sakamakon": "the result",
  "idanunsu": "their eyes",
  "kufai": "scar",
  "tentunansu": "their tents",
  "taɗin": "the conversation",
  "rauni": "wound",
  "rabo": "share",
  "littafin": "the book",
  "gamshi": "satisfied",
  "saniya": "cow",
  "ƙahoninsa": "his horns",
  "kofatansa": "his feet",
  "kamammun": "captured",
  "motsi": "movement",
  "biranen": "the cities",
  "mallake": "possession",
  "gāje": "inheritance",
  "kunyansu": "their shame",
  "jinkiri": "postponement",
  "je": "go",
  "ɓuyana": "hiding",
  "katangata": "my wall",
  "cutar": "the disease",
  "labarin": "the story",
  "yawansa": "his number",
  "naka": "for you",
  "furfura": "gray",
  "wahaloli": "difficulties",
  "girmana": "my size",
  "ta'azantar": "comfort",
  "solomon": "solomon",
  "shari'arka": "your case",
  "filin": "the field",
  "ciyayin": "the grass",
  "yalwata": "plenty",
  "sauran": "the rest",
  "kabilun": "the tribes",
  "lashe": "won",
  "gandu": "tribute",
  "sheba": "look",
  "seba": "seba",
  "gajiyayyu": "tired",
  "jininsu": "their blood",
  "doguwar": "long",
  "dominsa": "for him",
  "bisan": "even",
  "itatuwansa": "his trees",
  "bazu": "expand",
  "ciyayi": "vegetation",
  "gona": "farm",
  "kammala": "completed",
  "addu'o'in": "the prayers",
  "yesse": "yes",
  "ƙafana": "my feet",
  "kusan": "nearly",
  "zamewa": "slide",
  "jikunansu": "their bodies",
  "mallaki": "possession",
  "mutanensu": "their people",
  "hannuwa": "hands",
  "annoba": "epidemic",
  "bashe": "broken",
  "ƙarshensu": "their end",
  "jefar": "throw away",
  "share": "clear",
  "mafarki": "dream",
  "almarai": "legends",
  "ɓaci": "violation",
  "jahili": "barbarian",
  "shawararka": "your advice",
  "raunana": "afflict",
  "kiwonka": "raising you",
  "saya": "purchase",
  "daɗewa": "increase",
  "wadda": "who",
  "sawunka": "your feet",
  "maƙiyanka": "your enemies",
  "kakkafa": "kakafa",
  "tutotinsu": "their flags",
  "wāshin": "the part",
  "gatura": "axe",
  "itatuwa": "trees",
  "ragargaje": "net",
  "sassaƙar": "the sculpture",
  "katako": "beam",
  "gudumarsu": "their hammer",
  "ƙurmus": "kurmus",
  "ƙazantar": "dirty",
  "mazaunin": "the resident",
  "annabawan": "the prophets",
  "ragu": "decrease",
  "waninmu": "another one of us",
  "maƙiya": "enemies",
  "rigarka": "your shirt",
  "dodo": "monster",
  "dodon": "dragon",
  "bubbuɗe": "open",
  "maɓulɓulai": "sources",
  "busar": "whistle",
  "koguna": "rivers",
  "rani": "summer",
  "damina": "summer",
  "kurciyarka": "your dove",
  "rayukan": "the souls",
  "lungu": "recess",
  "mabukata": "the needy",
  "muradinka": "your wishes",
  "ihun": "shout",
  "zaɓi": "choice",
  "ƙayyadadden": "specified",
  "mutanenta": "her people",
  "ginshiƙan": "the columns",
  "ƙahoninku": "your horns",
  "miƙaƙƙen": "extended",
  "gauraye": "mixed",
  "yaji": "spice",
  "tas": "bag",
  "tentinsa": "his tent",
  "salem": "salem",
  "kibiyoyin": "the arrows",
  "takuban": "swords",
  "makaman": "the weapons",
  "jarumawa": "heroes",
  "barcinsu": "their sleep",
  "tsawatawarka": "your rebuke",
  "keken": "the bike",
  "hukunci": "condemnation",
  "tsira": "survive",
  "rawaninka": "your crown",
  "maƙwabta": "neighbors",
  "gajiya": "fatigue",
  "ta'azantu": "comfort",
  "rufewa": "closing",
  "shekarun": "age",
  "waƙoƙina": "my songs",
  "kāsa": "fail",
  "tausayinsa": "his compassion",
  "i": "yes",
  "mu'ujizanka": "your miracles",
  "mu'ujizai": "miracles",
  "yusuf": "yusuf",
  "gaske": "really",
  "tsawanka": "your height",
  "guguwa": "hurricane",
  "walƙiyarka": "your lightning",
  "garke": "herd",
  "musa": "don't",
  "haruna": "aaron",
  "koyarwata": "my teaching",
  "misalai": "examples",
  "ya'yanmu": "our children",
  "ƙa'idodi": "rules",
  "kakanni": "grandparents",
  "umarnansa": "his command",
  "kakanninsu": "their ancestors",
  "taurinkai": "stubbornness",
  "alkawarin": "the promise",
  "dokarsa": "his law",
  "zowan": "coming",
  "girgije": "cloud",
  "tsage": "disrupt",
  "gangan": "intentionally",
  "kwaɗayi": "desire",
  "ɓulɓulo": "developed",
  "nama": "meat",
  "gaskata": "admit",
  "manna": "paste",
  "hatsin": "the grain",
  "burodin": "the bread",
  "mala'iku": "angels",
  "saki": "release",
  "tsuntsaye": "birds",
  "yashi": "sand",
  "sansaninsu": "their camp",
  "ishe": "enough",
  "ƙuna": "burn",
  "karkashe": "kill",
  "ƙiba": "fat",
  "yankan": "cutting",
  "matasan": "hybrid",
  "banmamakinsa": "his miracle",
  "shekarunsu": "their age",
  "natse": "calm down",
  "dutsensu": "their mountain",
  "fansarsu": "their redemption",
  "laifofinsu": "their crimes",
  "dawowa": "coming back",
  "tsokane": "provoke",
  "mu'ujizansa": "his miracles",
  "kogunansu": "their rivers",
  "tarin": "collection",
  "ƙudajen": "the flies",
  "kwaɗin": "the frog",
  "wahalshe": "difficulty",
  "fāra": "start",
  "amfanin": "the benefits",
  "gonakinsu": "their farms",
  "ɗango": "relative",
  "nasu": "theirs",
  "jaura": "move",
  "shanunsu": "their cows",
  "tumakinsu": "their sheep",
  "aradun": "the thunder",
  "ɓacin": "the pain",
  "hallakarwa": "destruction",
  "mafari": "beginner",
  "mazantakansu": "their masculinity",
  "tentunan": "the tents",
  "ham": "ham",
  "ƙalau": "look",
  "kame": "arrested",
  "ƙasashensu": "their countries",
  "zaunar": "sitting",
  "kabilan": "the tribe",
  "tanƙwararren": "bent",
  "masujadansu": "their mosques",
  "tudu": "mountain",
  "kishinsa": "his jealousy",
  "gumakansu": "their idols",
  "shilo": "shiloh",
  "tentin": "the tent",
  "akwatin": "the box",
  "hannuwan": "your hands",
  "matasansu": "their youth",
  "matansu": "their wives",
  "firistocinsu": "their priests",
  "gwaurayensu": "their widows",
  "barcinsa": "his sleep",
  "buguwar": "drunk",
  "ɗakin": "the room",
  "kiwon": "raising",
  "makiyayin": "the shepherd",
  "makiyayinsu": "their shepherd",
  "mutuncin": "the dignity",
  "gawawwakin": "the corpses",
  "bayinka": "your servant",
  "jikin": "the body",
  "binne": "bury",
  "matattu": "the dead",
  "kishinka": "your jealousy",
  "yarda": "accept",
  "mulkokin": "kingdoms",
  "zunubanmu": "our sins",
  "allahnsu": "their god",
  "fansar": "redemption",
  "nishe": "sigh",
  "nishen": "sigh",
  "cinyoyin": "the thighs",
  "makiyayarka": "your pasture",
  "cetu": "salvation",
  "ciyar": "feed",
  "cikakken": "complete",
  "saiwa": "root",
  "inuwarsa": "his shadow",
  "rassansa": "its branches",
  "miƙe": "rise",
  "tohonsa": "his bud",
  "rurrushe": "crushed",
  "bangayensa": "its parts",
  "tsinke": "cut off",
  "inabinsa": "his grapes",
  "aladu": "culture",
  "cinsa": "count",
  "wurinmu": "our place",
  "saiwar": "the root",
  "renar": "renar",
  "inabinka": "your wine",
  "fara": "start",
  "ganga": "container",
  "rago": "ram",
  "tsakiya": "middle",
  "bikinmu": "our celebration",
  "ƙa'ida": "rule",
  "farilla": "precept",
  "fahimta": "understand",
  "kafaɗunku": "your shoulders",
  "kwando": "basket",
  "damuwarku": "your worries",
  "girgijen": "the cloud",
  "meriba": "good luck",
  "baƙon": "the stranger",
  "cikinku": "inside you",
  "bakinku": "your mouth",
  "taurare": "hardened",
  "dabararsu": "their strategy",
  "hannuna": "my hand",
  "maƙiyansu": "their enemies",
  "hukuncinsu": "their judgment",
  "alkama": "wheat",
  "ƙosar": "fed up",
  "shugabanta": "direct",
  "zartar": "pass",
  "goyi": "support",
  "hakkin": "the right",
  "fahimci": "understand",
  "cik": "full",
  "ishmayel": "ishmael",
  "hagirawa": "agirawa",
  "ammon": "ammon",
  "amalek": "amalek",
  "assuriya": "assyria",
  "lot": "lot",
  "midiyan": "midian",
  "sisera": "sisera",
  "yabin": "praise",
  "kishon": "kishon",
  "en": "en",
  "dor": "dor",
  "juji": "dump",
  "oreb": "oreb",
  "zeyib": "zeib",
  "sarakunansu": "their kings",
  "zeba": "pick up",
  "zalmunna": "my cruelty",
  "wuraren": "the places",
  "tsiron": "the plant",
  "hurawa": "blowing",
  "harshen": "the language",
  "guguwarka": "your storm",
  "taƙaici": "summary",
  "filayen": "the fields",
  "tsatsewa": "interrupt",
  "sheƙa": "nest",
  "ƙyanƙyashe": "hatch",
  "ya'yanta": "her brothers",
  "farko": "beginning",
  "tafkuna": "ponds",
  "kowanne": "each one",
  "shafaffenka": "your anointed",
  "dabam": "separately",
  "gwammaci": "rather",
  "ƙasarka": "your country",
  "tsararraki": "generations",
  "wauta": "silly",
  "ƙasarmu": "our country",
  "sumba": "kiss",
  "amfaninta": "its use",
  "addu'ar": "the prayer",
  "gafartawa": "forgive",
  "kwatanta": "imagine",
  "jinkirin": "the delay",
  "alamar": "the sign",
  "harsashinsa": "his shell",
  "rahab": "rahab",
  "rubuta": "write",
  "maɓulɓulaina": "maɓulɓulaina",
  "cikinki": "inside you",
  "heman": "the same",
  "dangin": "the family",
  "ezra": "ezra",
  "ware": "allocate",
  "turmushe": "marriage",
  "raƙumanka": "your waves",
  "kange": "restrain",
  "lahira": "afterlife",
  "ƙarami": "small",
  "razanarka": "your heart",
  "ƙaunatattuna": "my loved ones",
  "etan": "ethane",
  "bawana": "my servant",
  "zuriyarka": "your offspring",
  "talikan": "creature",
  "samaniya": "the sky",
  "tsarkaka": "pure",
  "bantsoro": "bantsoro",
  "tumbatsa": "tumpa",
  "halicce": "created",
  "kudu": "south",
  "tabor": "scar",
  "tushen": "the source",
  "koyi": "learn",
  "ɗaukakarsu": "their glory",
  "ƙahonka": "your horn",
  "wahayi": "vision",
  "saurayi": "teenager",
  "haraji": "tax",
  "ƙahonsa": "his horn",
  "naɗa": "appoint",
  "farina": "farina",
  "fasa": "break",
  "ya'yansa": "his children",
  "dokata": "the law",
  "ƙa'idodina": "my rules",
  "umarnaina": "my orders",
  "sanda": "stick",
  "laifinsu": "their fault",
  "ambata": "mention",
  "ƙari": "additive",
  "tsarkina": "my purity",
  "amintacciyar": "reliable",
  "rawaninsa": "his crown",
  "katangansa": "his wall",
  "kagaransa": "his fortress",
  "maƙwabtansa": "his neighbors",
  "rage": "reduce",
  "ƙuruciyarsa": "his childhood",
  "mayafin": "the veil",
  "mazauninmu": "our residence",
  "madawwami": "eternal",
  "komar": "return",
  "shekaru": "age",
  "sa'a": "good luck",
  "sabuwa": "new",
  "ciyawar": "the grass",
  "laifinmu": "our fault",
  "asirin": "the secret",
  "kwanakinmu": "our days",
  "shekarunmu": "our age",
  "tsawon": "length",
  "saba'in": "seventy",
  "tamanin": "eighty",
  "tsawonsu": "their length",
  "farauta": "hunt",
  "cututtuka": "diseases",
  "fikafikansa": "his wings",
  "bala'in": "disaster",
  "aukowa": "coming",
  "annobar": "the epidemic",
  "tsakar": "the middle",
  "umarci": "command",
  "mala'ikunsa": "his angels",
  "tallafe": "support",
  "ƙafarka": "your foot",
  "gamsheƙa": "complete",
  "asabbaci": "saturday",
  "kiɗin": "the music",
  "ƙahona": "my horn",
  "zubo": "spill",
  "fāɗuwar": "the fall",
  "dabino": "date",
  "daddasa": "long ago",
  "ya'ya": "son",
  "tsufansu": "their old age",
  "ɗanye": "damp",
  "shar": "share",
  "sanye": "wearing",
  "matsar": "move",
  "kursiyin": "the throne",
  "fil": "pin",
  "azal": "azal",
  "tsawan": "length",
  "raƙuman": "the waves",
  "ƙa'idodinka": "your rules",
  "alƙalin": "the judge",
  "kisan": "the murder",
  "horo": "punishment",
  "dokarka": "your law",
  "tuni": "already",
  "alhini": "sadness",
  "ta'aziyyarka": "your comfort",
  "yiwu": "may",
  "muguntarsu": "their wickedness",
  "mahaliccinmu": "our creator",
  "makiyayansa": "his shepherds",
  "kulawarsa": "his care",
  "massa": "mass",
  "kakanninku": "your ancestors",
  "arba'in": "forty",
  "rantsuwa": "oath",
  "fushina": "my anger",
  "hutuna": "my vacation",
  "tilas": "must",
  "gumaka": "idols",
  "tsarkakar": "pure",
  "tsibirai": "islands",
  "walƙiyarsa": "his lightning",
  "kakin": "coat",
  "yeahohn": "yes",
  "siffofi": "features",
  "hukunce": "judgement",
  "hukuncenka": "your judgment",
  "darjanta": "her honor",
  "karar": "the case",
  "girmanka": "your greatness",
  "banrazana": "i'm crazy",
  "firistocinsa": "his priests",
  "sama'ila": "sama'ila",
  "ginshiƙin": "the column",
  "farillansa": "his decrees",
  "makiyayarsa": "his pasture",
  "ƙofofinsa": "its doors",
  "madawwamiya": "eternal",
  "sha'anin": "the affair",
  "gidana": "my house",
  "ɓatanci": "libel",
  "renin": "renin",
  "tafiyarsa": "his journey",
  "ruɗun": "delusion",
  "ƙaryan": "lie",
  "jan": "red",
  "kamu": "caught",
  "rame": "limp",
  "ƙasusuwa": "bones",
  "mujiyar": "the owl",
  "mujiya": "owl",
  "faɗake": "wake up",
  "rufin": "the roof",
  "ɗaki": "room",
  "tsokanata": "provoke me",
  "la'ana": "curse",
  "toka": "ash",
  "duwatsunta": "her stones",
  "ƙurarta": "her dust",
  "roƙonsu": "their request",
  "hangi": "view",
  "tattaru": "gather",
  "gajartar": "abbreviated",
  "shekarunka": "your age",
  "farkon": "the beginning",
  "tsufe": "old",
  "alheransa": "his grace",
  "ƙuruciyarka": "your childhood",
  "gaggafa": "eagle",
  "gwargwadon": "according to",
  "cire": "deduction",
  "mahaifi": "mother",
  "fure": "flower",
  "masarautarsa": "his kingdom",
  "rundunarsa": "his army",
  "nufinsa": "his intention",
  "mulkinsa": "his rule",
  "naɗe": "fold",
  "yaƙinsa": "his battle",
  "saƙonsa": "his message",
  "tussanta": "her foundation",
  "ruga": "run",
  "kwaruruka": "valleys",
  "tsallakawa": "crossing",
  "jakunan": "the donkeys",
  "ƙishirwansu": "their thirst",
  "sheƙunansu": "their heels",
  "rassa": "branches",
  "ɗakinsa": "his room",
  "ƙoshiya": "khoshiya",
  "aikinsa": "his work",
  "nome": "nome",
  "fuska": "face",
  "sheƙunnansu": "their shenanigans",
  "shamuwa": "shamu",
  "gidanta": "her house",
  "fir": "fir",
  "awakin": "the goats",
  "tsagaggun": "cracked",
  "rema": "rema",
  "ƙididdigar": "the analysis",
  "maƙe": "dead",
  "abincinsu": "their food",
  "kogwanninsu": "their caves",
  "aikinka": "your job",
  "halittunka": "your creatures",
  "numfashinsu": "their breath",
  "halittu": "creatures",
  "gamshe": "satisfied",
  "ganinsu": "see them",
  "mamakin": "surprised",
  "hukuncen": "the judgment",
  "zaɓaɓɓensa": "his chosen one",
  "hukuncensa": "his judgment",
  "rantsuwar": "the oath",
  "ishaku": "isaac",
  "kan'ana": "small",
  "masarauta": "kingdom",
  "shafaffena": "my anointed",
  "annabawa": "the prophets",
  "lahani": "harm",
  "tanadinsu": "their provisions",
  "bawa": "slave",
  "sarƙa": "chain",
  "wuyansa": "his neck",
  "ƙarafa": "metal",
  "rigafaɗi": "advance",
  "sarakunansa": "his kings",
  "dattawa": "elders",
  "mamakinsa": "his surprise",
  "kifayensu": "their fish",
  "ƙasarsu": "their country",
  "kwaɗi": "frog",
  "ɗakunan": "the rooms",
  "ƙudaje": "flies",
  "cinnaku": "you",
  "samansu": "above them",
  "ɓaurensu": "their figs",
  "fāri": "drought",
  "fāran": "white",
  "ƙidayuwa": "calculation",
  "gonarsu": "their farm",
  "nunan": "show",
  "mazantakarsu": "their masculinity",
  "kabilansu": "their tribe",
  "mayafi": "veil",
  "roƙa": "beg",
  "makware": "makware",
  "zaɓaɓɓunsa": "his chosen ones",
  "nasarar": "the victory",
  "zaɓaɓɓunka": "your chosen ones",
  "al'ummarka": "your community",
  "alheranka": "your grace",
  "shawararsa": "his decision",
  "sha'awarsu": "their desire",
  "cuta": "disease",
  "datan": "data",
  "iyalin": "the family",
  "abiram": "abiram",
  "ƙuno": "burn",
  "horeb": "horeb",
  "gunkin": "the icon",
  "zubi": "zubi",
  "sauke": "download",
  "siffar": "shape",
  "godo": "thank you",
  "ni'ima": "blessing",
  "gunaguni": "complaints",
  "ba'al": "ba'al",
  "feyor": "feyor",
  "finehas": "phinehas",
  "mataki": "step",
  "ayana": "there is",
  "kalmomi": "words",
  "cuɗanya": "mixing",
  "al'adunsu": "their culture",
  "aljanu": "demons",
  "zub": "teeth",
  "ƙazantu": "dirty",
  "karuwanci": "prostitution",
  "ƙyamar": "disgust",
  "nace": "persist",
  "tausayinsu": "their pity",
  "amin": "amen",
  "fansassu": "redeemed",
  "ƙishirwa": "thirst",
  "damuwarsu": "their worries",
  "shayar": "drink",
  "mayunwata": "i'm hungry",
  "sarƙoƙin": "the chains",
  "tsintsinke": "pick it up",
  "ƙyamaren": "disgust",
  "umarninsa": "his instructions",
  "tsinduma": "work",
  "azabarsu": "their punishment",
  "halinsu": "their behavior",
  "tangaɗi": "talk",
  "tafkunan": "the ponds",
  "samo": "found",
  "girbe": "harvest",
  "yawansu": "their number",
  "garkunansu": "their herds",
  "bala'i": "disaster",
  "iyalansu": "their families",
  "tsayayyiya": "stable",
  "farkar": "wake up",
  "hulan": "hat",
  "sandana": "stick",
  "tattaka": "tread",
  "addu'o'insa": "his prayers",
  "shugabanci": "direction",
  "matarsa": "his wife",
  "gwauruwa": "a widow",
  "bara": "servant",
  "koransu": "chasing them",
  "binsa": "follow him",
  "marayunsa": "his orphans",
  "mahaifiyarsa": "his mother",
  "la'antarwa": "curse",
  "rigarsa": "his shirt",
  "jikinsa": "his body",
  "ɗamara": "belt",
  "sakayyar": "say",
  "zargina": "blame me",
  "maganganu": "statements",
  "gwiwoyina": "my knees",
  "kawunansu": "their heads",
  "damar": "opportunity",
  "yeahohna": "yes",
  "matashin": "the young man",
  "rundunarka": "your army",
  "ranarka": "your day",
  "raɓar": "the dew",
  "firist": "priest",
  "melkizedek": "melchizedek",
  "tarawa": "collect",
  "gawawwaki": "corpses",
  "tsayayyu": "stable",
  "yinsu": "do them",
  "mafarin": "the beginning",
  "al'amuransa": "his affairs",
  "kyautansa": "his gift",
  "ciza": "bite",
  "sha'awace": "interest",
  "sha'awacen": "the desire",
  "bayin": "servants",
  "mahaifiyar": "the mother",
  "mallakarsa": "his property",
  "kalla": "contemplate",
  "kika": "read",
  "tafki": "lake",
  "bakuna": "bows",
  "kunnuwa": "ears",
  "ƙanshi": "fragrance",
  "taimakonsu": "their help",
  "garkuwarsu": "their shield",
  "ya'yanku": "your children",
  "mahalicci": "creator",
  "saman": "the top",
  "tsananin": "the intensity",
  "rikicewana": "my confusion",
  "baiwarka": "your gift",
  "sarƙoƙi": "chains",
  "tsakiyarki": "your middle",
  "amincin": "trust",
  "ƙudan": "the flies",
  "ture": "push",
  "waƙata": "my song",
  "ƙofar": "the door",
  "magina": "builder",
  "haskensa": "his light",
  "kwanoni": "bowls",
  "hannunmu": "our hand",
  "bagade": "altar",
  "umarnanka": "your command",
  "koyon": "learning",
  "matashi": "cushion",
  "maganarka": "your words",
  "dokokin": "the rules",
  "bakinka": "your mouth",
  "farillanka": "your precepts",
  "ƙosa": "tired",
  "koyaushe": "always",
  "mashawartana": "my mentors",
  "koyarwar": "the teaching",
  "kankan": "tight",
  "sonkai": "your self",
  "kunyata": "i'm ashamed",
  "ƙaunarsu": "their love",
  "ta'aziyyata": "my comfort",
  "keta": "breach",
  "saba": "used to",
  "matakaina": "my steps",
  "gaggauta": "rush",
  "aboki": "friend",
  "siffanta": "describe",
  "salkar": "salkar",
  "ƙetare": "omit",
  "azabana": "my torment",
  "kāsawa": "shortage",
  "malamaina": "my teachers",
  "ɗanɗanon": "the taste",
  "fitila": "lamp",
  "gādona": "my inheritance",
  "gwale": "bad",
  "muhimmanci": "importance",
  "yaudararsu": "their deception",
  "datti": "dirt",
  "fahimi": "understanding",
  "karya": "lie",
  "fassarar": "translation",
  "maganganunka": "your words",
  "ilimi": "education",
  "malalowa": "flow",
  "rafi": "stream",
  "kishina": "my jealousy",
  "biris": "beer",
  "alkawuranka": "your promises",
  "dawwammame": "eternal",
  "manufata": "my purpose",
  "alkawarta": "her promise",
  "koyarwarka": "your teaching",
  "sanannu": "famous",
  "ɓatacciyar": "lost",
  "tunkiya": "sheep",
  "haurawa": "go up",
  "damuwata": "my worries",
  "yaudara": "cheat",
  "tsintsiya": "broom",
  "kaitona": "alas",
  "meshek": "mesh",
  "kedar": "cedar",
  "tsaronka": "your security",
  "gyangyaɗi": "leprosy",
  "inuwa": "shadow",
  "shigarka": "your entrance",
  "fitarka": "get out",
  "ƙofofinki": "your doors",
  "harhaɗe": "combined",
  "kabilu": "tribes",
  "kursiyoyin": "the chairs",
  "salamar": "peace",
  "ƙaunarki": "love you",
  "katangarki": "your castle",
  "fadodinki": "your palaces",
  "wadatarki": "your prosperity",
  "bayi": "servants",
  "maigidansu": "their master",
  "baiwa": "faculty",
  "uwargijiyarta": "her mistress",
  "gefenmu": "our side",
  "auka": "collapse",
  "fushinsu": "their anger",
  "kwashe": "take away",
  "ambaliya": "flood",
  "hauka": "insanity",
  "rabon": "the ratio",
  "nagartattu": "good",
  "karkatattun": "twisted",
  "hanyoyi": "ways",
  "bakunanmu": "our mouths",
  "dominsu": "for them",
  "dominmu": "for us",
  "wadatarmu": "our prosperity",
  "negeb": "negative",
  "girbi": "harvest",
  "iri": "brand",
  "shuki": "plant",
  "dammuna": "i'm worried",
  "gininta": "her building",
  "tsaro": "security",
  "latti": "late",
  "mazan": "men",
  "ƙuruciya": "childhood",
  "korinsa": "chase him",
  "ƙarawa": "indictment",
  "albarku": "congratulations",
  "matarka": "your wife",
  "kuringar": "kurungar",
  "tohon": "bud",
  "teburinka": "your table",
  "wadatar": "supply",
  "manoma": "farmers",
  "kunyoyinsu": "their shame",
  "rufi": "roof",
  "albarkar": "the blessing",
  "kunnuwanka": "your ears",
  "dami": "too much",
  "al'amura": "matters",
  "haƙura": "patience",
  "yaron": "the boy",
  "yaye": "wean",
  "mazauni": "resident",
  "efrata": "ephrata",
  "ƙaro": "crash",
  "ya'ar": "son",
  "hutunka": "your holiday",
  "suturta": "clothes",
  "firistocinka": "your priests",
  "tabbataccen": "positive",
  "matalautanta": "matalautanta",
  "firistocinta": "her priest",
  "tsarkakanta": "her purity",
  "ƙaho": "horn",
  "yan'uwa": "brothers",
  "gemu": "beard",
  "gemun": "the beard",
  "rigunansa": "his clothes",
  "albarkarsa": "his blessings",
  "mahaliccin": "the creator",
  "zurfafansu": "their depth",
  "ajiyarsa": "his savings",
  "tsirkiyarku": "your family",
  "fir'auna": "pharaoh",
  "sihon": "sihon",
  "amoriyawa": "amorites",
  "og": "and",
  "numfashi": "breath",
  "lawi": "levi",
  "iyayengiji": "lords",
  "ganewarsa": "his recognition",
  "haskoki": "rays",
  "tsakiyarsa": "the middle of it",
  "ƙasƙancinmu": "our humbleness",
  "kogunan": "the rivers",
  "babilon": "babylon",
  "rassan": "branches",
  "rataye": "hanging",
  "garayunmu": "our harps",
  "kamunmu": "our catch",
  "baƙuwar": "the guest",
  "iyawarsa": "his ability",
  "ihu": "shout",
  "tushenta": "its source",
  "miki": "ulcer",
  "jariranki": "your babies",
  "kāsassu": "countries",
  "fitata": "my exit",
  "kwanciyata": "my bed",
  "santa": "santa",
  "halicci": "creation",
  "mahaifar": "the womb",
  "asirce": "secret",
  "fasali": "schedule",
  "ƙirgansu": "count them",
  "yashin": "the sand",
  "nufi": "purpose",
  "shirin": "the plan",
  "ragarsu": "their net",
  "fansana": "redemption",
  "garkuwoyin": "the shields",
  "bukatunsu": "their needs",
  "masifun": "the disaster",
  "farauci": "hunting",
  "ɗagawa": "lifting",
  "ƙasusuwanmu": "our bones",
  "gunagunina": "my complaints",
  "damata": "my chance",
  "matsananciyar": "extreme",
  "nagarin": "good",
  "yatsotsina": "my fingers",
  "sammanka": "together",
  "karɓa": "accept",
  "takobin": "the sword",
  "ƙuruciyarsu": "their childhood",
  "tsiren": "plant",
  "ginshiƙai": "columns",
  "sassaƙa": "carpentry",
  "adon": "decoration",
  "rumbunanmu": "our warehouses",
  "tanadi": "savings",
  "tumakinmu": "our sheep",
  "filayenmu": "our fields",
  "shanunmu": "our cows",
  "katangarmu": "our castle",
  "zuwan": "coming",
  "titunanmu": "our streets",
  "girmansa": "his size",
  "ganewar": "the diagnosis",
  "bikin": "the celebration",
  "sarautarka": "your kingdom",
  "alkawuransa": "his promises",
  "rusunar": "bow down",
  "makafi": "blind",
  "allahnki": "your god",
  "isra'ilan": "israel",
  "raunanar": "weak",
  "ɗaɗɗaura": "tight",
  "miyakunsu": "their superiors",
  "kowannensu": "each of them",
  "hankaki": "raven",
  "iyakokinki": "your limits",
  "ulu": "wool",
  "hazo": "mist",
  "ƙananan": "small",
  "sanyin": "the cold",
  "narkar": "dissolve",
  "iskarsa": "his air",
  "dusar": "the snow",
  "hadirin": "attendance",
  "dabbobin": "the animals",
  "samari": "boys",
  "tsofaffi": "the elderly",
  "mahaliccinsu": "their creator",
  "sarkinsu": "their king",
  "gadajensu": "their beds",
  "ɗau": "take",
  "kakaki": "trumpet",
  "af": "air force",
  "ar": "accounts receivable",
  "ba": "not",
  "di": "drill instructor",
  "era": "earned run average",
  "abida": "abidan",
  "addinin": "religious",
  "afirka": "africa",
  "agari": "aggravation",
  "aguiyi-ironsi": "agui-ironsteri",
  "ahusatin": "ahusin",
  "akaro": "akaso",
  "akayi": "it was",
  "alama": "sign",
  "alamu": "patterns",
  "almasihu": "christ",
  "an-katakonana": "an-brants",
  "annabi": "prophet",
  "antun": "certain",
  "aramin": "welcome",
  "arewa": "north",
  "arewacin": "north of",
  "arziƙinta": "rich",
  "asali": "origin",
  "asalin": "origin",
  "ayin": "ivence",
  "baban": "pound",
  "bace": "disappear",
  "bahaushe": "approval",
  "bakwai": "seven",
  "balewa": "back",
  "bamu": "don",
  "bankin": "bank",
  "barin": "abandon",
  "barkai": "felow",
  "basasa": "bases",
  "bayan": "behind",
  "bazara": "spring",
  "be": "exist",
  "benin": "bishin",
  "biki": "holiday",
  "birane": "urban",
  "birnin": "city",
  "birtaniya": "uk",
  "biyu": "two",
  "buga": "print",
  "bulala": "whip",
  "burtaniya": "uk",
  "canza": "change",
  "cewar": "saying",
  "chadi": "chad",
  "char": "tea",
  "cikin": "in",
  "da": "and",
  "daban": "differently",
  "daddare": "the night",
  "daga": "from",
  "daka": "carately",
  "dake": "with you",
  "dalar": "dollars",
  "daya": "one",
  "dimokaradiya": "democracy",
  "dodanci": "dodya",
  "doka": "law",
  "duhu": "darkness",
  "duk": "all",
  "dukkan": "all",
  "dukkansu": "all",
  "duniya": "world",
  "fadar": "palace",
  "fadin": "clasp",
  "faɗi": "fall",
  "fuskanci": "face",
  "gabas": "east",
  "gado": "bed",
  "gano": "find",
  "garuruwa": "towns",
  "gaɓar": "sorrow",
  "gida": "home",
  "gine-ekwatorial": "build-ekwatorial",
  "girma": "bulk",
  "gobir": "ob",
  "guda": "single",
  "gudanar": "manage",
  "gudanarwa": "conduct",
  "gunan": "the fruit",
  "gwamna": "governor",
  "gwamnatance": "principle",
  "hadari": "storm",
  "haihuwar": "the birth",
  "hanyar": "path",
  "harshe": "tongue",
  "hasason-tamar": "had a-tamar",
  "haskala": "incorrect",
  "hausawa": "hausa",
  "hayakuwa": "fucked",
  "haɗe": "combination",
  "haɗin": "link",
  "hudu": "four",
  "hukuma": "agency",
  "hukuncin": "sentence",
  "hula": "cap",
  "huta": "rest",
  "idan": "if",
  "illar": "election",
  "inda": "wherever",
  "ingila": "england",
  "ingilishi": "english",
  "inyamuranci": "beds",
  "inyamuri": "mechanally",
  "irin": "breed",
  "isah": "jesus",
  "isancinza": "ivailor",
  "issakar": "issar",
  "itace": "she is",
  "iyaka": "border",
  "izini": "authorization",
  "i̇shak": "i̇hak",
  "jamhuriyar": "republic",
  "jamusawa": "germans",
  "janairun": "brother",
  "jaridar": "newspaper",
  "jera": "join",
  "jerin": "list",
  "jihohi": "states",
  "jini": "blood",
  "johnson": "a man's penis",
  "juyin": "revolution",
  "ka-abrama": "you-abrama",
  "kadesh": "madesh",
  "kafa": "establish",
  "kafin": "before",
  "kai": "you",
  "kaini": "take me",
  "kajin": "chicks",
  "kama-karya": "caught",
  "kamar": "like",
  "kamaru": "camouflage",
  "kanada": "you have",
  "kanana": "small",
  "kare": "protect",
  "karfin": "the strength",
  "kasance": "remain",
  "kasar": "country",
  "kasuwa": "market",
  "katin": "card",
  "kawai": "only",
  "kayin": "nephy",
  "kaza": "chicken",
  "kecin": "cheolution",
  "kilichoongezwa": "kilomhoongezwa",
  "kima": "appraisal",
  "kimanin": "about",
  "kiranta": "my call",
  "kirista": "christ",
  "kiristoci": "christians",
  "kirkirar": "created",
  "kirkiri": "create",
  "kitso": "kites",
  "kofyar": "doors",
  "kogin": "the river",
  "kowa": "each",
  "koyaya": "however",
  "koyo": "learning",
  "ku-abrahama": "you-abhama",
  "ku-abrama": "you-abrama",
  "ku-adamu": "you-adam",
  "kudanci": "southwards",
  "kudancin": "south",
  "kuka": "cry",
  "kuka-adamu": "crying",
  "kulawa": "care",
  "kullum": "ever",
  "kulunsa": "support",
  "kulūmriyya": "kurūriya",
  "kuma": "same to you",
  "kusar": "colute",
  "kutsayabilesin": "the",
  "kutsayan": "shock",
  "kwallon": "ball",
  "kyauta": "grant",
  "loda": "upload",
  "lokaci": "while",
  "lokoja": "occasion",
  "madobi": "homey",
  "mafi": "more",
  "magana": "speaking",
  "magogi": "eraser",
  "maido": "restore",
  "majalisar": "post",
  "majansa": "his portrait",
  "mallaka": "possess",
  "mallakewa": "own",
  "mamaye": "conquest",
  "manyan": "great",
  "masu": "owners",
  "mata": "women",
  "matakin": "level",
  "matsahin": "trouble",
  "matsakaiciyar": "average",
  "matsayin": "status",
  "maye": "intoxication",
  "memba": "member",
  "miladiya": "ambition",
  "miliyan": "million",
  "misali": "example",
  "mishi": "misuse",
  "moriya": "mori",
  "mudai": "donkey",
  "muke": "we",
  "mulki": "rule",
  "mulkin": "rule",
  "munkyawa": "weep",
  "musulmai": "muslims",
  "mutane": "people",
  "mutanen": "the people",
  "najeriya": "nigeria",
  "namama": "mammai",
  "nan": "here",
  "naso-ke": "naso",
  "nawa": "how much",
  "nawonina": "my own",
  "naˈdʒɪəriyə": "nadʒɪəriyəriyəriyəriyəriy",
  "ne": "it is",
  "ne-ayi": "is",
  "neja": "near",
  "neman": "seek",
  "neme": "seek",
  "nesancinza": "nensazarza",
  "nijar": "niger",
  "nijeria": "igata",
  "nijeriya": "nigeria",
  "nisi": "of a decree",
  "niɔ̌nsɔ": "nɔ̌nnsɔ",
  "niˈdʒɪəriyə": "nidʒɪəriaə",
  "nnabbi": "nnabin",
  "nodus": "a problem",
  "nojidilafe": "nojidare",
  "nuhu": "noah",
  "nuna": "show",
  "raba": "share",
  "ran-tsan-kazo": "the day-perfume",
  "ranar": "the day",
  "rashawa": "corruption",
  "rasu": "die",
  "ratsa": "intersect",
  "rike": "handle",
  "roba": "rubber",
  "rushe": "destroy",
  "ruwa": "water",
  "saboda": "through",
  "safinani": "safinani safina",
  "samarin": "the younger",
  "samu": "find",
  "sannan": "then",
  "sanya": "place",
  "sauƙaƙe": "facilitate",
  "shagari": "shop",
  "shanu": "cattle",
  "shekara": "year",
  "shela": "proclamation",
  "shugaban": "president",
  "shugabannin": "heads",
  "soari": "soak",
  "soja": "military",
  "sojoji": "soldiers",
  "sojojin": "forces",
  "sosai": "much",
  "suka": "themselves",
  "sukukuntiensa": "sukukunartien",
  "sukuni": "leisure",
  "suna": "name",
  "ta-haka": "by-so",
  "tabbas": "surely",
  "tabbatacciyar": "verification",
  "tafawa": "file",
  "taimako": "help",
  "talaka": "for the poor",
  "talakawa": "ordinary",
  "tambaya": "ask",
  "tana": "she",
  "tanin-tsira": "airi",
  "tarayyar": "partner",
  "tasa": "bowl",
  "tasowa": "upon",
  "tattalin": "prepare",
  "tauri": "hardship",
  "tekun": "coast",
  "teyaŋŋamba": "welcome to teyeen",
  "tsakanin": "between",
  "tsakiyar": "central",
  "tsaren": "the",
  "tsarin": "system",
  "tsaye": "stand",
  "tsirarun": "tower",
  "tsoka": "muscle",
  "tsoran": "anxiety",
  "tubal-kajin": "tubal-chicken",
  "tubali": "brick",
  "tubalkainowa": "tubkankain",
  "tufanla": "millmark",
  "turai": "europe",
  "turawa": "pressure",
  "uhrilahjansa": "uhrahtahja hisa",
  "uku": "three",
  "vacay": "a vacation",
  "waje": "outside",
  "walagirira": "sincerity",
  "wammukisa": "wivukisc",
  "wannan": "this",
  "wasan": "game",
  "wata": "moon",
  "watan": "month",
  "wato": "also",
  "waya": "cable",
  "wayewa": "civilization",
  "waɗanda": "those",
  "yabawa": "praise",
  "yafa": "forgive",
  "yakama": "yakam",
  "yalagira": "plenty",
  "yamma": "west",
  "yammacin": "western",
  "yamuwa": "yama",
  "yana": "it's",
  "yanayin": "the weather",
  "yankin": "the area",
  "yanziyako": "ban back",
  "yanzu": "now",
  "yara": "kids",
  "yaran": "the kids",
  "yarbanci": "funny",
  "yaren": "language",
  "yarika": "her",
  "yarurruka": "top",
  "yasa": "makes",
  "yaso": "sister",
  "yatsa": "thumb",
  "yau": "today",
  "yawafica": "rebest",
  "yawan": "population",
  "yawuiira": "crawling",
  "yayana": "my",
  "yayin": "while",
  "yayita": "yajin",
  "yaƙin": "battle",
  "zaba": "choice",
  "zabe": "poll",
  "zaben": "election",
  "zama": "remain",
  "zamani": "period",
  "zaran-defony": "optional-defony",
  "zaune": "sitting",
  "zaɓa": "select",
  "zaɓaɓɓun": "chosen",
  "zaɓen": "the option",
  "zaɓensa": "air",
  "zuwa": "arrival",
  "ƙabilar": "the tribe",
  "ƙabilu": "triand",
  "ƙabilun": "nervous",
  "ƙarfi": "strength",
  "ƙarni": "centuries",
  "ƙasa": "ground",
  "ƙasar": "country",
  "ƙasashe": "country",
  "ƙasashen": "lands",
  "ƙkasar": "the",
  "ƙungiyoyin": "countries",
  "ƙunshi": "package",
  "ƴan": "sister",
  "ƴanci": "freedom",
  "ƴancin": "freedom",
  "ɗan": "participant",
  "ɗaukar": "take",
  "ɗaukarta": "takea",
  "ɗaya": "one",
  "ɗinkin": "sheet",
  "ה-mmd": "ה- mmd",
  "وalkali": "وت"
 }
}