{
 "yi": {
  "bible": "the christian scriptures",
  "אֱלִישָׁמָע": "aֱliisha",
  "אֱלִישׁוּעַ": "aֱlisy",
  "אִֿילִיַאא": "yiddish",
  "אִידוּמיאָה": "audimioh",
  "אִירַאן": "ailon",
  "אֶלְיָדָע": "eliadah",
  "אֶתְבַּעַל": "atheall",
  "אַל-אַֿקְצָא": "al-ajincs",
  "אַל-יֶחְסָר": "al-joshr",
  "אַל-מַדִֿינָה": "al-madinah",
  "אַל-מֻקַֿדָס": "al-moursa",
  "אַל-קִיבְּלַתָֿיְין": "al-kiib",
  "אַלְאִסְרַֿאא": "all-tialy",
  "אַלְמִעְרַֿאג": "alaiain",
  "אַלְקֻֿדְס": "bess in the",
  "אַמְנוֹן": "department",
  "אַמְפַה": "arix",
  "אָיִן": "oh",
  "אָמָּן": "oman",
  "אָת-אִיזֶבֶל": "otal",
  "אֿוּלָא": "elii",
  "אאיצטדינין": "aytistinin",
  "אביבעל": "abibel",
  "אדוניבעל": "adoberill",
  "אדיין": "odain",
  "אדננה": "littlen",
  "אוּמָנים": "whom",
  "אוּשוּ": "verifying",
  "אוטושי": "motui",
  "און": "and",
  "אונא": "accept",
  "אונטש": "ino",
  "אוקלידס": "ukrainized",
  "אידא": "jews",
  "איזיל": "bail",
  "איירליינס": "airlines",
  "איצטרובלין": "itstrank",
  "איריא": "iya",
  "אירמס": "youoms",
  "אלעי": "ali",
  "אנבּל": "divil",
  "אנדזיט": "agency",
  "אנוסים": "audience",
  "אנשן": "commend",
  "אפוּלוּם": "reveal",
  "אפיך": "pages",
  "אפיקומן": "umpharnt",
  "אראך": "king",
  "אריחים": "sealim",
  "בְּיַלְדוּתֶיךָ": "b",
  "בְגָדֶיךָ": "benefo",
  "בְצִיּוֹן": "tuch",
  "בִּירוּשָׁלִַם": "bilirozhal",
  "בֶּהָמוֹן": "baamo",
  "בַּחַיִּים": "uthaim",
  "בַּשַׁבָּת": "abr",
  "בַעֲמָלוֹ": "everyson",
  "בָּאֳנִי": "baim",
  "בָּחוּר": "anxiety",
  "בָּצְעָה": "baedh",
  "באַל-מַדִֿינָה": "bal-maidinah",
  "בוושלטס": "jeward",
  "ביודע": "biude",
  "ביינארט": "at night",
  "בייקינגו": "bikingu",
  "בלום": "flower",
  "במכונה": "th annoyant",
  "בערודי": "berudi",
  "בריטיש": "british",
  "בשולחן": "relationship",
  "בשעריך": "wherse",
  "גאבור": "gabel",
  "גאמא": "gammos",
  "גיסטרא": "verstra",
  "גפי": "gfi",
  "גפר": "grof",
  "גרלך": "spade",
  "דְּמַלְכוּתָא": "shalloda",
  "דִּינָא": "dami",
  "דָּאג": "lawy",
  "דָּוד": "doudy",
  "דאביק": "panic",
  "דארזא": "lying",
  "דארץ": "where",
  "דוויל": "dvil",
  "דזקני": "dzcany",
  "דזרט": "durt",
  "די-פולריים": "the -ifter",
  "דידיע": "dedie",
  "דימם": "dimmly",
  "דינרין": "dinren",
  "דיפאטו": "defaults",
  "דיפפטיד": "deffted",
  "דיץ": "these",
  "דיר": "you",
  "דער": "the",
  "דערבא": "dumb",
  "דערלה": "light",
  "דקטיל": "dctill",
  "הִיפּוֹס": "people",
  "הִשָּבַע": "gabase",
  "הַבְּהֵמָה": "hamday",
  "הַכֶּסֶף": "hazhech",
  "הַשַּׂר": "baper",
  "האָקוֹניטון": "hockinn",
  "האבניים": "wat",
  "האורבניים": "haughline",
  "האכדי": "did",
  "האריחים": "lashims",
  "הגמון": "hagmun",
  "הגעוואלד": "sorse",
  "היסטידין": "hultididist",
  "הירודים": "huties",
  "הכדורסל": "hardser",
  "הלימוד": "hlimud",
  "המדרגות": "scoop",
  "המעוניינים": "hmoonynim",
  "המתמטיקה": "samittick",
  "הצבעוניות": "merit",
  "הצבעוניים": "towe",
  "השולחן": "person",
  "וְדָע": "undah",
  "וְהַבַּיִת": "sheak",
  "וְחָרָשֵׁי": "buthabihoi",
  "וַיִּבְנוּ": "andauaua",
  "וּבַעֲמָלְךָ": "taskia",
  "וּמְאוּמָה": "whomah",
  "וּמַאֲכָל": "sheong",
  "ודייוויד": "udiywid",
  "ווֹיווֹד": "cesh",
  "וויסקאיה": "wacoh",
  "ווקאס": "wcas",
  "וושלטס": "awhety",
  "ויבהל": "sowl",
  "ויבן": "above",
  "ויגד": "souged",
  "ויוון": "stove",
  "ויטאוטאס": "cutsis",
  "ויטע": "as",
  "וישע": "early",
  "ומעץ": "inferish",
  "ונאפּוֹקה": "unsposen",
  "ונשמרת": "unsisp",
  "וסִיַנּוּ": "use",
  "וסִיסּוּ": "usesions",
  "וערף": "ugf",
  "ורוניק": "largel",
  "ושהטעם": "and",
  "זֶענט": "zhen",
  "זבצקי": "zbtsky",
  "זיבענבערגן": "zubenbern",
  "זיין": "be",
  "זילא": "zail",
  "זילזולו": "zilzulou",
  "זימוגן": "somick",
  "זימנא": "zomma",
  "חֶלְקְךָ": "halati",
  "חַיֵּי": "haesiel",
  "חֿילדוַּה": "fade",
  "חֿילכּו": "sym",
  "חרוסת": "diverity",
  "טאהר": "theah",
  "טח": "fore",
  "טנט": "tnt",
  "טעמ": "temple",
  "טריד": "tried",
  "טריניטי": "trinity",
  "טריפפטיד": "triffed",
  "יְבִיאֲךָ": "yobriaֲch",
  "יִבְחָר": "indid",
  "יִרוּסַלִֿים": "joachansim",
  "יִשְׂבַּע": "nitaze",
  "יִשָּׂא": "ishaha",
  "יֵינֶךָ": "yeshinh",
  "יַארֶסצַייטֶן": "sonschel",
  "יַם": "azam",
  "יָדְךָ": "yid",
  "יָפִיעַ": "ipay",
  "יָרְדוּ": "yesterday",
  "יודל": "yodl",
  "יוט": "euch",
  "יוליאני": "julii",
  "יוניס": "unite",
  "יוניקס": "unix",
  "יימר": "apony",
  "ימעט": "alet",
  "ירב": "irb",
  "ישויך": "hit",
  "כְּשֶׁבָּא": "asshan yah",
  "כְבָר": "cerebaker",
  "כִנּוֹר": "town",
  "כיי": "speci",
  "כיין": "charm",
  "כנטע": "dunt",
  "כקרקע": "change",
  "לִבְּךָ": "labil",
  "לִינְגְּוַּה": "hebrews",
  "לַחְמֶךָ": "samao",
  "לַטִינַה": "savine",
  "לַצִּדֹנִים": "lessili",
  "לוּבִיָא": "libiah",
  "לוקין": "lucin",
  "לחַפּוֹת": "lap",
  "לטש": "lunch",
  "ליגאז": "legal",
  "ליגנדים": "al",
  "ליט": "lit",
  "ליריק": "liyric",
  "לפרחים": "",
  "לץ": "lts",
  "מֶֿכָּה": "mahah",
  "מָאָתַיִם": "mathaments",
  "מָצוּי": "mess",
  "מאגן": "mug",
  "מאונטיין": "mountane",
  "מדליין": "circumcle",
  "מהמוזיקה": "mhmusical",
  "מהרופאים": "morphhatz",
  "מוויילס": "meals",
  "מוניציפליות": "munsolizer",
  "מופעם": "mufum",
  "מורא": "fear",
  "מזבחותם": "jzzomizam",
  "מזדעזע": "mdze",
  "מיזו-ווארי": "mizu-follow",
  "מילייא": "melio",
  "מינות": "russian",
  "מיניינן": "mininn",
  "מיסק": "misk",
  "מיר": "me",
  "מכנען": "rupt",
  "מלימודים": "milimestion",
  "ממטיר": "mmtir",
  "ממעמדהּ": "mention",
  "מערבּוּ": "west",
  "מערק": "merc",
  "משמחן": "meshet",
  "משקאות": "judgment",
  "נִשָּבַע": "nathanah",
  "נָטְלָה": "nottah",
  "נָתַתָּה": "nettyta",
  "נהירין": "nehin",
  "נוּקלֵאָז": "doesn't often help",
  "נוור": "nerve",
  "נטרא": "utra",
  "ניזיל": "nizil",
  "סֻכּוֹ": "marer",
  "סוּף": "end",
  "סוויטן": "sweek",
  "סומאטו": "sumato",
  "סטיריקון": "steak",
  "סיכּו": "sykhu",
  "סילי": "sili",
  "סימא": "simi",
  "סלוּצק": "slud",
  "סנדערקע": "sniff",
  "סנדרקע": "sndrke",
  "סנר": "snr",
  "סענדערקע": "sender",
  "עֲצַבִּים": "united states",
  "עִנְיָן": "everyrian",
  "עֵינוֹ": "esinos",
  "עַיִן": "aoth",
  "עָרוֹם": "schoam",
  "עזיבעל": "ezybel",
  "על-סגולה": "al-song",
  "עמילאז": "emilzz",
  "ענוים": "exhaust",
  "עסיקתא": "vicination",
  "עפרא": "empha",
  "עציו": "lyu",
  "ערף": "erf",
  "ערקי": "airy",
  "פּוֹלִין": "puohin",
  "פֿוֹינִיקְס": "resports",
  "פֿישקע": "fish",
  "פאשא": "pahas",
  "פובליציסטיים": "fublicistime",
  "פונדקי": "fitikki",
  "פטם": "ftm",
  "פיל": "much",
  "פילס": "feels",
  "פירוקלסטיים": "fireplay",
  "פירוקסן": "fourquanc",
  "פירסטיין": "firestine",
  "פלגא": "plfes",
  "פליגא": "fire",
  "פליימינג": "flawing",
  "פריינגפן-ארקנסו": "frying -unknsu",
  "פרענא": "fren",
  "צִוַפַּלַרְחֻחְפַּךּ": "zaudaheb",
  "צאר": "tsrs",
  "צבעונים": "berevim",
  "צוּ": "to",
  "צי": "jerk",
  "ציסטאין": "pistoline",
  "צען": "ten",
  "קְטַן-עָלִים": "citan-ealam",
  "קַבִּין": "qibn",
  "קַרְתְּ": "constance",
  "קָאקוּלִימָה": "cucksazhah",
  "קָנֹה": "cnior",
  "קאדיס": "codis",
  "קאזלי": "clasley",
  "קאלב": "cap",
  "קאפוליע": "copuliance",
  "קהלות": "churtil",
  "קוה": "cuh",
  "קוק": "view",
  "קורייטי": "curate",
  "קורלי": "curly",
  "קטיל": "quiet",
  "קיושו": "kiushu",
  "קיטיליסיר": "kitzyr",
  "קייהין": "kiyhin",
  "קייוגן": "chain",
  "קייטן": "bonds",
  "קינגיו": "qingyu",
  "קירגיזסטן": "kyrgyzist",
  "קירין": "fire",
  "קלוויניסט": "clivist",
  "קלייב": "club",
  "קלך": "poud",
  "קלציט": "clinc",
  "קעביד": "kebid",
  "קראים": "commercial",
  "קרומער": "crummer",
  "קרק": "cc",
  "רָמוֹן": "camon",
  "רָצָה": "razah",
  "ראויין": "ranane",
  "רבניצקי": "rbnitsky",
  "רוּתֶּנִי": "trade",
  "רובידיום": "ruby",
  "רוסן": "russin",
  "ריוקאן": "ruyan",
  "ריין": "pure",
  "ריקישי": "recishi",
  "שָׁמוּר": "sumander",
  "שָׁקֵד": "shׁcq",
  "שָׂרִיד": "sharid",
  "שאמיר": "begat",
  "שויו": "chair",
  "שטינמץ": "principles",
  "שטראם": "troulay",
  "שטרייכמן": "scram",
  "שיחין": "ski",
  "שיסל": "dish",
  "שיפן": "ships",
  "שיפרין": "sofry",
  "שיץ": "sheets",
  "שמהירות": "shearns",
  "שמען": "merm",
  "שמתמחים": "satersomanatsy",
  "תְבוּאָה": "thrioh",
  "תִּמְצָא": "people",
  "תנחום": "tan"
 }
}